[{
  "_id": {
    "$oid": "682679cfcce9e4416363282d"
  },
  "filename": "00_00.jpg",
  "text": "Doll %ui; TARdeeri",
  "translated": "[Translation Error: translate_text() got an unexpected keyword argument 'target_lang']",
  "image_path": "resized_00_00.jpg"
},
{
  "_id": {
    "$oid": "682679d6cce9e4416363282e"
  },
  "filename": "00_01.jpg",
  "text": "Americas Best Value Nvortu lnn uia 7167711.3882 VAGNCY",
  "translated": "[Translation Error: translate_text() got an unexpected keyword argument 'target_lang']",
  "image_path": "resized_00_01.jpg"
},
{
  "_id": {
    "$oid": "682679ddcce9e4416363282f"
  },
  "filename": "00_03.jpg",
  "text": "aladins JUnt JOIit o JnaGrl Hin 73 5",
  "translated": "[Translation Error: translate_text() got an unexpected keyword argument 'target_lang']",
  "image_path": "resized_00_03.jpg"
},
{
  "_id": {
    "$oid": "682679e3cce9e44163632830"
  },
  "filename": "00_04.jpg",
  "text": "Avgnte Gaicens FLORIST Ql SCHOOL O1 FloRAL DESIG$",
  "translated": "[Translation Error: translate_text() got an unexpected keyword argument 'target_lang']",
  "image_path": "resized_00_04.jpg"
},
{
  "_id": {
    "$oid": "682679eacce9e44163632831"
  },
  "filename": "00_05.jpg",
  "text": "Muzio",
  "translated": "[Translation Error: translate_text() got an unexpected keyword argument 'target_lang']",
  "image_path": "resized_00_05.jpg"
},
{
  "_id": {
    "$oid": "682679f0cce9e44163632832"
  },
  "filename": "00_06.jpg",
  "text": "(COTId EAMMgtonront; Hi VAVE RuNNER Ator ATV;",
  "translated": "[Translation Error: translate_text() got an unexpected keyword argument 'target_lang']",
  "image_path": "resized_00_06.jpg"
},
{
  "_id": {
    "$oid": "682679f8cce9e44163632833"
  },
  "filename": "00_07.jpg",
  "text": "Ahahei Band INSTRUMENTS",
  "translated": "[Translation Error: translate_text() got an unexpected keyword argument 'target_lang']",
  "image_path": "resized_00_07.jpg"
},
{
  "_id": {
    "$oid": "682679ffcce9e44163632834"
  },
  "filename": "00_08.jpg",
  "text": "harLe YARI DPION Mle 0 0",
  "translated": "[Translation Error: translate_text() got an unexpected keyword argument 'target_lang']",
  "image_path": "resized_00_08.jpg"
},
{
  "_id": {
    "$oid": "68267a0acce9e44163632835"
  },
  "filename": "00_09.jpg",
  "text": "E roddwyill STqxe Qvar J,UUU NEW Wom D",
  "translated": "[Translation Error: translate_text() got an unexpected keyword argument 'target_lang']",
  "image_path": "resized_00_09.jpg"
},
{
  "_id": {
    "$oid": "68267a1ccce9e44163632836"
  },
  "filename": "00_10.jpg",
  "text": "0 HAMDURORS ukbron V(owe @tnaeta 8 \"SeRvCS} Ro? _",
  "translated": "[Translation Error: translate_text() got an unexpected keyword argument 'target_lang']",
  "image_path": "resized_00_10.jpg"
},
{
  "_id": {
    "$oid": "68267a2dcce9e44163632837"
  },
  "filename": "00_11.jpg",
  "text": "ZNeecome7 MLLS Gird Fa",
  "translated": "[Translation Error: translate_text() got an unexpected keyword argument 'target_lang']",
  "image_path": "resized_00_11.jpg"
},
{
  "_id": {
    "$oid": "68267a94639009eee1be671d"
  },
  "filename": "00_00.jpg",
  "text": "Doll %ui; TARdeeri",
  "translated": "[Translation Error: translate_text() got an unexpected keyword argument 'target_lang']",
  "image_path": "resized_00_00.jpg"
},
{
  "_id": {
    "$oid": "68267a99639009eee1be671e"
  },
  "filename": "00_01.jpg",
  "text": "Americas Best Value Nvortu lnn uia 7167711.3882 VAGNCY",
  "translated": "[Translation Error: translate_text() got an unexpected keyword argument 'target_lang']",
  "image_path": "resized_00_01.jpg"
},
{
  "_id": {
    "$oid": "68267a9f639009eee1be671f"
  },
  "filename": "00_03.jpg",
  "text": "aladins JUnt JOIit o JnaGrl Hin 73 5",
  "translated": "[Translation Error: translate_text() got an unexpected keyword argument 'target_lang']",
  "image_path": "resized_00_03.jpg"
},
{
  "_id": {
    "$oid": "68267aa6639009eee1be6720"
  },
  "filename": "00_04.jpg",
  "text": "Avgnte Gaicens FLORIST Ql SCHOOL O1 FloRAL DESIG$",
  "translated": "[Translation Error: translate_text() got an unexpected keyword argument 'target_lang']",
  "image_path": "resized_00_04.jpg"
},
{
  "_id": {
    "$oid": "68267ab1639009eee1be6721"
  },
  "filename": "00_05.jpg",
  "text": "Muzio",
  "translated": "[Translation Error: translate_text() got an unexpected keyword argument 'target_lang']",
  "image_path": "resized_00_05.jpg"
},
{
  "_id": {
    "$oid": "68267ac3639009eee1be6722"
  },
  "filename": "00_06.jpg",
  "text": "(COTId EAMMgtonront; Hi VAVE RuNNER Ator ATV;",
  "translated": "[Translation Error: translate_text() got an unexpected keyword argument 'target_lang']",
  "image_path": "resized_00_06.jpg"
},
{
  "_id": {
    "$oid": "68267ad5639009eee1be6723"
  },
  "filename": "00_07.jpg",
  "text": "Ahahei Band INSTRUMENTS",
  "translated": "[Translation Error: translate_text() got an unexpected keyword argument 'target_lang']",
  "image_path": "resized_00_07.jpg"
},
{
  "_id": {
    "$oid": "68267b0f70486a0ce1ef1b2a"
  },
  "filename": "00_00.jpg",
  "text": "Doll %ui; TARdeeri",
  "translated": "Doll %ui;Tart",
  "image_path": "resized_00_00.jpg"
},
{
  "_id": {
    "$oid": "68267b1670486a0ce1ef1b2b"
  },
  "filename": "00_01.jpg",
  "text": "Americas Best Value Nvortu lnn uia 7167711.3882 VAGNCY",
  "translated": "Americas Best Value Nvortu lnn uia 7167711.3882 VAGNCY",
  "image_path": "resized_00_01.jpg"
},
{
  "_id": {
    "$oid": "68267b1e70486a0ce1ef1b2c"
  },
  "filename": "00_03.jpg",
  "text": "aladins JUnt JOIit o JnaGrl Hin 73 5",
  "translated": "aladins JUt JonGrl Hin 73 5",
  "image_path": "resized_00_03.jpg"
},
{
  "_id": {
    "$oid": "68267b2470486a0ce1ef1b2d"
  },
  "filename": "00_04.jpg",
  "text": "Avgnte Gaicens FLORIST Ql SCHOOL O1 FloRAL DESIG$",
  "translated": "Avgnte Gaicens FLORIST Ql SCHOOL O1 FloRAL DESIG$",
  "image_path": "resized_00_04.jpg"
},
{
  "_id": {
    "$oid": "68267b2b70486a0ce1ef1b2e"
  },
  "filename": "00_05.jpg",
  "text": "Muzio",
  "translated": "Muzio",
  "image_path": "resized_00_05.jpg"
},
{
  "_id": {
    "$oid": "68267b3370486a0ce1ef1b2f"
  },
  "filename": "00_06.jpg",
  "text": "(COTId EAMMgtonront; Hi VAVE RuNNER Ator ATV;",
  "translated": "(Cotid Eammgtonront; Hi VAVE RUNNER Actor ATV;",
  "image_path": "resized_00_06.jpg"
},
{
  "_id": {
    "$oid": "68267b3a70486a0ce1ef1b30"
  },
  "filename": "00_07.jpg",
  "text": "Ahahei Band INSTRUMENTS",
  "translated": "Ahahei Band INSTRUMENTS",
  "image_path": "resized_00_07.jpg"
},
{
  "_id": {
    "$oid": "68267b4070486a0ce1ef1b31"
  },
  "filename": "00_08.jpg",
  "text": "harLe YARI DPION Mle 0 0",
  "translated": "0 0",
  "image_path": "resized_00_08.jpg"
},
{
  "_id": {
    "$oid": "68267b4670486a0ce1ef1b32"
  },
  "filename": "00_09.jpg",
  "text": "E roddwyill STqxe Qvar J,UUU NEW Wom D",
  "translated": "E Roddwyill stqxe qvar j, uuu new wom d",
  "image_path": "resized_00_09.jpg"
},
{
  "_id": {
    "$oid": "68267b4b70486a0ce1ef1b33"
  },
  "filename": "00_10.jpg",
  "text": "0 HAMDURORS ukbron V(owe @tnaeta 8 \"SeRvCS} Ro? _",
  "translated": "0 HAMDURORS ukbron V(owe @tnaeta 8 \"SeRvCS} Ro? _",
  "image_path": "resized_00_10.jpg"
},
{
  "_id": {
    "$oid": "68267b5070486a0ce1ef1b34"
  },
  "filename": "00_11.jpg",
  "text": "ZNeecome7 MLLS Gird Fa",
  "translated": "ZNeecome7 MLLS Gird Fa",
  "image_path": "resized_00_11.jpg"
},
{
  "_id": {
    "$oid": "68267b5670486a0ce1ef1b35"
  },
  "filename": "00_12.jpg",
  "text": "SUBWAR",
  "translated": "SUBWAR",
  "image_path": "resized_00_12.jpg"
},
{
  "_id": {
    "$oid": "68267b5c70486a0ce1ef1b36"
  },
  "filename": "00_13.jpg",
  "text": "KFC 131",
  "translated": "KFC 131",
  "image_path": "resized_00_13.jpg"
},
{
  "_id": {
    "$oid": "68267b6270486a0ce1ef1b37"
  },
  "filename": "00_14.jpg",
  "text": "PANCAKE HOUSE Fkhsa Ouginal",
  "translated": "PANCAKE HOUSE Fkhsa Ouginal",
  "image_path": "resized_00_14.jpg"
},
{
  "_id": {
    "$oid": "68267b6770486a0ce1ef1b38"
  },
  "filename": "00_15.jpg",
  "text": "CAN CAT  [SUSHI SHOGUN \"CUISIESE| CUISINE VKHSHD ALL YG [CAN EX",
  "translated": "CAN CAT  [SUSHI SHOGUN \"CUISIESE| CUISINE VKHSHD ALL YG [CAN EX",
  "image_path": "resized_00_15.jpg"
},
{
  "_id": {
    "$oid": "68267b6c70486a0ce1ef1b39"
  },
  "filename": "00_16.jpg",
  "text": "Now #rViNIC DJ SUBS) Breakfask pe4",
  "translated": "Now #rViNIC DJ SUBS) Breakfask pe4",
  "image_path": "resized_00_16.jpg"
},
{
  "_id": {
    "$oid": "68267b7370486a0ce1ef1b3a"
  },
  "filename": "00_17.jpg",
  "text": "EconoLodge  SPA SuiteS 0odes n acoi S FTu",
  "translated": "Economology Spa 0oDODS NOT SHO",
  "image_path": "resized_00_17.jpg"
},
{
  "_id": {
    "$oid": "68267b7970486a0ce1ef1b3b"
  },
  "filename": "00_18.jpg",
  "text": "Daysinn bSuites",
  "translated": "Daysinn bSuites",
  "image_path": "resized_00_18.jpg"
},
{
  "_id": {
    "$oid": "68267b7f70486a0ce1ef1b3c"
  },
  "filename": "00_19.jpg",
  "text": "Comlort NN",
  "translated": "Comlorin nn",
  "image_path": "resized_00_19.jpg"
},
{
  "_id": {
    "$oid": "68267b8570486a0ce1ef1b3d"
  },
  "filename": "01_01.jpg",
  "text": "Budget",
  "translated": "Budget",
  "image_path": "resized_01_01.jpg"
},
{
  "_id": {
    "$oid": "68267b8b70486a0ce1ef1b3e"
  },
  "filename": "01_02.jpg",
  "text": "SOLS 3",
  "translated": "SOLS 3",
  "image_path": "resized_01_02.jpg"
},
{
  "_id": {
    "$oid": "68267b9270486a0ce1ef1b3f"
  },
  "filename": "01_03.jpg",
  "text": "Public Storage",
  "translated": "Public Storage",
  "image_path": "resized_01_03.jpg"
},
{
  "_id": {
    "$oid": "68267b9870486a0ce1ef1b40"
  },
  "filename": "01_04.jpg",
  "text": "ehell",
  "translated": "ehell",
  "image_path": "resized_01_04.jpg"
},
{
  "_id": {
    "$oid": "68267b9f70486a0ce1ef1b41"
  },
  "filename": "01_05.jpg",
  "text": "OEnterprise 0",
  "translated": "Oenterprise 0",
  "image_path": "resized_01_05.jpg"
},
{
  "_id": {
    "$oid": "68267ba670486a0ce1ef1b42"
  },
  "filename": "01_06.jpg",
  "text": "Ale",
  "translated": "But",
  "image_path": "resized_01_06.jpg"
},
{
  "_id": {
    "$oid": "68267bad70486a0ce1ef1b43"
  },
  "filename": "01_07.jpg",
  "text": "CHANTERELLE $",
  "translated": "Chanterelle $",
  "image_path": "resized_01_07.jpg"
},
{
  "_id": {
    "$oid": "68267bb370486a0ce1ef1b44"
  },
  "filename": "01_09.jpg",
  "text": "Nicks Greek coaner",
  "translated": "Nicks Greek coaner",
  "image_path": "resized_01_09.jpg"
},
{
  "_id": {
    "$oid": "68267bb970486a0ce1ef1b45"
  },
  "filename": "01_10.jpg",
  "text": "Paless SheeSource M",
  "translated": "Paless SheeSource M",
  "image_path": "resized_01_10.jpg"
},
{
  "_id": {
    "$oid": "68267bbf70486a0ce1ef1b46"
  },
  "filename": "01_11.jpg",
  "text": "GOODWILL",
  "translated": "GOODWILL",
  "image_path": "resized_01_11.jpg"
},
{
  "_id": {
    "$oid": "68267bc570486a0ce1ef1b47"
  },
  "filename": "01_13.jpg",
  "text": "700 Cl7? ThE EFek ool Stuff Bran pparel Promotional Products In",
  "translated": "700 Cl7? ThE EFek ool Stuff Bran pparel Promotional Products In",
  "image_path": "resized_01_13.jpg"
},
{
  "_id": {
    "$oid": "68267bcc70486a0ce1ef1b48"
  },
  "filename": "01_14.jpg",
  "text": "SIX FEET UNDER col",
  "translated": "SIX FEET UNDER col",
  "image_path": "resized_01_14.jpg"
},
{
  "_id": {
    "$oid": "68267bd270486a0ce1ef1b49"
  },
  "filename": "01_15.jpg",
  "text": "SuPER 8HO1El",
  "translated": "SuPER 8HO1El",
  "image_path": "resized_01_15.jpg"
},
{
  "_id": {
    "$oid": "68267bd970486a0ce1ef1b4a"
  },
  "filename": "01_16.jpg",
  "text": "EM B 4 & $",
  "translated": "I b 4 & $",
  "image_path": "resized_01_16.jpg"
},
{
  "_id": {
    "$oid": "68267bdf70486a0ce1ef1b4b"
  },
  "filename": "01_17.jpg",
  "text": "CARROLL Street 04E",
  "translated": "CARROLL Street 04E",
  "image_path": "resized_01_17.jpg"
},
{
  "_id": {
    "$oid": "68267be570486a0ce1ef1b4c"
  },
  "filename": "01_18.jpg",
  "text": " QUALITY HOTEL FDC",
  "translated": "QUALITY HOTEL FDC",
  "image_path": "resized_01_18.jpg"
},
{
  "_id": {
    "$oid": "68267bed70486a0ce1ef1b4d"
  },
  "filename": "01_19.jpg",
  "text": "1 Nertz DU:",
  "translated": "1 nertz you:",
  "image_path": "resized_01_19.jpg"
},
{
  "_id": {
    "$oid": "68267bf570486a0ce1ef1b4e"
  },
  "filename": "02_01.jpg",
  "text": "GRAND Jor ZASE TEM CENTRAL 4I2S \"275 ENGER &",
  "translated": "Grand Dorraz Tal Tem Central 4i2s \"275 A &",
  "image_path": "resized_02_01.jpg"
},
{
  "_id": {
    "$oid": "68267bfc70486a0ce1ef1b4f"
  },
  "filename": "02_02.jpg",
  "text": "THB REDWOD LUAURY NNIMENIS 41 S Eutawv K Now Lcasing]",
  "translated": "THB REDWOD LUAURY NNIMENIS 41 S Eutawv K Now Lcasing]",
  "image_path": "resized_02_02.jpg"
},
{
  "_id": {
    "$oid": "68267c0570486a0ce1ef1b50"
  },
  "filename": "02_03.jpg",
  "text": "PaulLaureNgeidunan commurn Hiar achaol 1400 ORLEANS STREET",
  "translated": "PAVEOLAUE ENDITANAN CONTURN HAR ACHAOL 1400 Orleans Street",
  "image_path": "resized_02_03.jpg"
},
{
  "_id": {
    "$oid": "68267c0c70486a0ce1ef1b51"
  },
  "filename": "02_04.jpg",
  "text": "The   Balimore 4#aru Win[ V PUB FAVORI R CATERING BUFFALO 1-4455 CAMDEN_PUB WWw camdenp Ot ONMDEN UG) SPens Dratt rafternst Kuraoke !",
  "translated": "The   Balimore 4#aru Win[ V PUB FAVORI R CATERING BUFFALO 1-4455 CAMDEN_PUB WWw camdenp Ot ONMDEN UG) SPens Dratt rafternst Kuraoke !",
  "image_path": "resized_02_04.jpg"
},
{
  "_id": {
    "$oid": "68267c1570486a0ce1ef1b52"
  },
  "filename": "02_05.jpg",
  "text": "Chase Brexton Health Services, Inc.",
  "translated": "Chase Brexton Health Services, Inc.",
  "image_path": "resized_02_05.jpg"
},
{
  "_id": {
    "$oid": "68267c1d70486a0ce1ef1b53"
  },
  "filename": "02_06.jpg",
  "text": "MARI BORO",
  "translated": "Great Boro",
  "image_path": "resized_02_06.jpg"
},
{
  "_id": {
    "$oid": "68267c2370486a0ce1ef1b54"
  },
  "filename": "02_07.jpg",
  "text": "(sidl @ust delcioug SAFFH",
  "translated": "(sidl @ust delcioug SAFFH",
  "image_path": "resized_02_07.jpg"
},
{
  "_id": {
    "$oid": "68267c2a70486a0ce1ef1b55"
  },
  "filename": "02_08.jpg",
  "text": "ReD SQUARE BELVEDERE IIU IIII SOPS",
  "translated": "ReD SQUARE BELVEDERE IIU IIII SOPS",
  "image_path": "resized_02_08.jpg"
},
{
  "_id": {
    "$oid": "68267c3370486a0ce1ef1b56"
  },
  "filename": "02_09.jpg",
  "text": "Mount Vecnon Hotel & Cafetecia FrsI REGISIER Fek",
  "translated": "Mount Vernon Hotel & Cafeteria FRSI Register Fek",
  "image_path": "resized_02_09.jpg"
},
{
  "_id": {
    "$oid": "68267c3a70486a0ce1ef1b57"
  },
  "filename": "02_10.jpg",
  "text": "END Road Wk KYRO PIZZA & GRILL HQ parrR MDoLE easterheninees FREE Mleest intrtnei Atallable Nut",
  "translated": "END Road Wk KYRO PIZZA & GRILL HQ parrR MDoLE easterheninees FREE Mleest intrtnei Atallable Nut",
  "image_path": "resized_02_10.jpg"
},
{
  "_id": {
    "$oid": "68267c4170486a0ce1ef1b58"
  },
  "filename": "02_11.jpg",
  "text": "urbirish Tmai CUISiNe",
  "translated": "Flying",
  "image_path": "resized_02_11.jpg"
},
{
  "_id": {
    "$oid": "68267c4770486a0ce1ef1b59"
  },
  "filename": "02_12.jpg",
  "text": "scores _ Scozes",
  "translated": "scores _ Scozes",
  "image_path": "resized_02_12.jpg"
},
{
  "_id": {
    "$oid": "68267c4f70486a0ce1ef1b5a"
  },
  "filename": "02_13.jpg",
  "text": "NoparnING Sotto  Sopra BAM-ZpM En 2p BPIA ~BPM PArknd H05 6pM-IeM 6",
  "translated": "Noparking Sothu Sopa Bon-JadpeM MMP BPA ~ BPM Park",
  "image_path": "resized_02_13.jpg"
},
{
  "_id": {
    "$oid": "68267c5770486a0ce1ef1b5b"
  },
  "filename": "02_14.jpg",
  "text": "42 CHIAPPARELLIS @Chi",
  "translated": "42 Chiappollis @chi",
  "image_path": "resized_02_14.jpg"
},
{
  "_id": {
    "$oid": "68267c5d70486a0ce1ef1b5c"
  },
  "filename": "02_15.jpg",
  "text": "FPDEESSONAL CONTACTS FORIEYES EYEGLASSES BYE EXAMS OSHEAS 5004oFF 2505 AFTAfia 328 SALE 99",
  "translated": "FPDEESSONAL CONTACTS FORIEYES EYEGLASSES BYE EXAMS OSHEAS 5004oFF 2505 AFTAfia 328 SALE 99",
  "image_path": "resized_02_15.jpg"
},
{
  "_id": {
    "$oid": "68267c6570486a0ce1ef1b5d"
  },
  "filename": "02_16.jpg",
  "text": "PICKLES PUB pickles   Pub Wise  Latima  daamk Heri 2 For5e  BeeR bi0 Flu Game dat Specials {",
  "translated": "PICKLES PUB pickles   Pub Wise  Latima  daamk Heri 2 For5e  BeeR bi0 Flu Game dat Specials {",
  "image_path": "resized_02_16.jpg"
},
{
  "_id": {
    "$oid": "68267c6b70486a0ce1ef1b5e"
  },
  "filename": "02_17.jpg",
  "text": "CHHTRE STREET GALLERY TOWER APARTMENT HOMES",
  "translated": "CHHTRE STREET GALLERY TOWER APARTMENT HOMES",
  "image_path": "resized_02_17.jpg"
},
{
  "_id": {
    "$oid": "68267c7170486a0ce1ef1b5f"
  },
  "filename": "02_19.jpg",
  "text": "BROWNS ARCADE DR HAIR SALON 'OGsIDED INSIDE CLEal EXPE ALTERA Spe RYCLEA",
  "translated": "BROWNS ARCADE DR HAIR SALON 'OGsIDED INSIDE CLEal EXPE ALTERA Spe RYCLEA",
  "image_path": "resized_02_19.jpg"
},
{
  "_id": {
    "$oid": "68267c7a70486a0ce1ef1b60"
  },
  "filename": "03_00.jpg",
  "text": "MOUNTAIN SUN (PUB &BREWERY 41575",
  "translated": "MOUNTAIN SUN (PUB &BREWERY 41575",
  "image_path": "resized_03_00.jpg"
},
{
  "_id": {
    "$oid": "68267c8270486a0ce1ef1b61"
  },
  "filename": "03_01.jpg",
  "text": "Larry' $ Boot Fitting 1709 Spruce Street LGAS",
  "translated": "Larry' $ Boot Fitting 1709 Spruce Street LGAS",
  "image_path": "resized_03_01.jpg"
},
{
  "_id": {
    "$oid": "68267c8b70486a0ce1ef1b62"
  },
  "filename": "03_02.jpg",
  "text": "BEADS BEADS BEADS Ow 1 PEN",
  "translated": "BEADS BEADS BEADS Ow 1 PEN",
  "image_path": "resized_03_02.jpg"
},
{
  "_id": {
    "$oid": "68267c9370486a0ce1ef1b63"
  },
  "filename": "03_03.jpg",
  "text": "Gobrado Daily",
  "translated": "Gobrado Daily",
  "image_path": "resized_03_03.jpg"
},
{
  "_id": {
    "$oid": "68267c9d70486a0ce1ef1b64"
  },
  "filename": "03_05.jpg",
  "text": "Ha ANTKROPOLOC IE",
  "translated": "Hai heart",
  "image_path": "resized_03_05.jpg"
},
{
  "_id": {
    "$oid": "68267ca570486a0ce1ef1b65"
  },
  "filename": "03_06.jpg",
  "text": "WidI 6 0..",
  "translated": "WidI 6 0..",
  "image_path": "resized_03_06.jpg"
},
{
  "_id": {
    "$oid": "68267cae70486a0ce1ef1b66"
  },
  "filename": "03_07.jpg",
  "text": "WALANTUI BREWERY",
  "translated": "Walantui Brewery",
  "image_path": "resized_03_07.jpg"
},
{
  "_id": {
    "$oid": "68267cb870486a0ce1ef1b67"
  },
  "filename": "03_08.jpg",
  "text": "lumbberlie",
  "translated": "lumbberlie",
  "image_path": "resized_03_08.jpg"
},
{
  "_id": {
    "$oid": "68267cc070486a0ce1ef1b68"
  },
  "filename": "03_09.jpg",
  "text": "ARA COMMON THREADS Old & ncI",
  "translated": "ARA COMMON THREADS Old & ncI",
  "image_path": "resized_03_09.jpg"
},
{
  "_id": {
    "$oid": "68267cc970486a0ce1ef1b69"
  },
  "filename": "03_10.jpg",
  "text": "macys",
  "translated": "MAYS",
  "image_path": "resized_03_10.jpg"
},
{
  "_id": {
    "$oid": "68267cd470486a0ce1ef1b6a"
  },
  "filename": "03_11.jpg",
  "text": "DRASSERIE TENTEN ITEN <",
  "translated": "Drasserie Tenten Ititet <",
  "image_path": "resized_03_11.jpg"
},
{
  "_id": {
    "$oid": "68267cdc70486a0ce1ef1b6b"
  },
  "filename": "03_12.jpg",
  "text": "TRIDENT",
  "translated": "TRIDENT",
  "image_path": "resized_03_12.jpg"
},
{
  "_id": {
    "$oid": "68267ce470486a0ce1ef1b6c"
  },
  "filename": "03_13.jpg",
  "text": "DOLAN'S I)cA\"? STEAKS [ SEAFOOD Wine Opirits",
  "translated": "DOLAN'S I)cA\"? STEAKS [ SEAFOOD Wine Opirits",
  "image_path": "resized_03_13.jpg"
},
{
  "_id": {
    "$oid": "68267ced70486a0ce1ef1b6d"
  },
  "filename": "03_14.jpg",
  "text": "BES | Indian Luncl HIMALAYAS 2010 I4tn STREET He",
  "translated": "BES | Indian Luncl HIMALAYAS 2010 I4tn STREET He",
  "image_path": "resized_03_14.jpg"
},
{
  "_id": {
    "$oid": "68267cf570486a0ce1ef1b6e"
  },
  "filename": "03_15.jpg",
  "text": "7ox Fao Ru REDEDHHON HEAT",
  "translated": "7ox Fao Ru REDEDHHON HEAT",
  "image_path": "resized_03_15.jpg"
},
{
  "_id": {
    "$oid": "68267cff70486a0ce1ef1b6f"
  },
  "filename": "03_16.jpg",
  "text": "scooters KymcO [BEPEE Siadlinje",
  "translated": "scooters KymcO [BEPEE Siadlinje",
  "image_path": "resized_03_16.jpg"
},
{
  "_id": {
    "$oid": "68267d0a70486a0ce1ef1b70"
  },
  "filename": "03_18.jpg",
  "text": "BARNSLEY TIRB CO. HOkoha",
  "translated": "Barnsley TIRB CO.Hokoha",
  "image_path": "resized_03_18.jpg"
},
{
  "_id": {
    "$oid": "68267d1370486a0ce1ef1b71"
  },
  "filename": "03_19.jpg",
  "text": "RockYMAOUNTS",
  "translated": "RockYMAOUNTS",
  "image_path": "resized_03_19.jpg"
},
{
  "_id": {
    "$oid": "68267d1b70486a0ce1ef1b72"
  },
  "filename": "04_00.jpg",
  "text": "ISan RadfoShadkk ~Fernando]",
  "translated": "I have a response to your adult ~ Fernando]",
  "image_path": "resized_04_00.jpg"
},
{
  "_id": {
    "$oid": "68267d2370486a0ce1ef1b73"
  },
  "filename": "04_01.jpg",
  "text": "GarN; MBATUDEu DI GIULIO CHIROPRACTIC AIc EC FRESH MeAT DELI PIKEM",
  "translated": "GarN; MBATUDEu DI GIULIO CHIROPRACTIC AIc EC FRESH MeAT DELI PIKEM",
  "image_path": "resized_04_01.jpg"
},
{
  "_id": {
    "$oid": "68267d2d70486a0ce1ef1b74"
  },
  "filename": "04_02.jpg",
  "text": "d KOTAYK KABOB aROcEaY] MSubL LMd D CHII Joo",
  "translated": "DOTION THAT COVE AROcEaY] MSubL LMd D CHII Joio",
  "image_path": "resized_04_02.jpg"
},
{
  "_id": {
    "$oid": "68267d3470486a0ce1ef1b75"
  },
  "filename": "04_03.jpg",
  "text": "MODERM 446 BARBER CUt COLOR ERM",
  "translated": "MODERM 446 BARBER CUt COLOR ERM",
  "image_path": "resized_04_03.jpg"
},
{
  "_id": {
    "$oid": "68267d3c70486a0ce1ef1b76"
  },
  "filename": "04_04.jpg",
  "text": "Ma, S MASTER NAILS 564410 MASTE ~GLeMOAKS NNAIH 563-44",
  "translated": "Ma, S MASTER NAILS 564410 MASTE ~GLeMOAKS NNAIH 563-44",
  "image_path": "resized_04_04.jpg"
},
{
  "_id": {
    "$oid": "68267d4470486a0ce1ef1b77"
  },
  "filename": "04_05.jpg",
  "text": "0 FIRST UNITED METHODIST CHURCH",
  "translated": "0 FIRST UNITED METHODIST CHURCH",
  "image_path": "resized_04_05.jpg"
},
{
  "_id": {
    "$oid": "68267d4b70486a0ce1ef1b78"
  },
  "filename": "04_06.jpg",
  "text": "0 burBANk FLORIST & GIFTS CHECK CASHL BURBAT FlorLS",
  "translated": "0 burBANk FLORIST & GIFTS CHECK CASHL BURBAT FlorLS",
  "image_path": "resized_04_06.jpg"
},
{
  "_id": {
    "$oid": "68267d5270486a0ce1ef1b79"
  },
  "filename": "04_07.jpg",
  "text": "T . Mobile  ~Glenoaks",
  "translated": "T . Mobile  ~Glenoaks",
  "image_path": "resized_04_07.jpg"
},
{
  "_id": {
    "$oid": "68267d5a70486a0ce1ef1b7a"
  },
  "filename": "04_11.jpg",
  "text": "M OCKE]MITH Lli BuPPLY SPEEDZONE [vom 540 Karge DOOR OPENERS",
  "translated": "M OCKE]MITH Lli BuPPLY SPEEDZONE [vom 540 Karge DOOR OPENERS",
  "image_path": "resized_04_11.jpg"
},
{
  "_id": {
    "$oid": "68267d6170486a0ce1ef1b7b"
  },
  "filename": "04_12.jpg",
  "text": "Phils Imports; Inc: HONDA AND ACURA EXPERTS",
  "translated": "Phils Imports; Inc: HONDA AND ACURA EXPERTS",
  "image_path": "resized_04_12.jpg"
},
{
  "_id": {
    "$oid": "68267d6970486a0ce1ef1b7c"
  },
  "filename": "04_13.jpg",
  "text": "opa Guoq CD 922 EAGLE MEDICAL SUPPLY 924 DS 922 h 38 59 om HEE\" MEAL SUPPU",
  "translated": "opa Guoq CD 922 EAGLE MEDICAL SUPPLY 924 DS 922 h 38 59 om HEE\" MEAL SUPPU",
  "image_path": "resized_04_13.jpg"
},
{
  "_id": {
    "$oid": "68267d6f70486a0ce1ef1b7d"
  },
  "filename": "04_14.jpg",
  "text": "920 M & M ACCOUNTANCY 920 3 MERS CLOSED | 21-6626",
  "translated": "920 M & M ACCOUNTANCY 920 3 MERS CLOSED | 21-6626",
  "image_path": "resized_04_14.jpg"
},
{
  "_id": {
    "$oid": "68267d7770486a0ce1ef1b7e"
  },
  "filename": "04_15.jpg",
  "text": "U} p8S Optometrist CLeMNGPLECE Dr: Melanya Garlbyan DPTOMETRIST ORED Guce Tedatningttonu 8494595 313 RoS Kseecw ow Dera ArhWeS",
  "translated": "A} with a storytelling by being aroused by Kelm Lablakar: Melanie Girlalia",
  "image_path": "resized_04_15.jpg"
},
{
  "_id": {
    "$oid": "68267d7f70486a0ce1ef1b7f"
  },
  "filename": "04_16.jpg",
  "text": "BLOCKBUSTER VIDEO",
  "translated": "BLOCKBUSTER VIDEO",
  "image_path": "resized_04_16.jpg"
},
{
  "_id": {
    "$oid": "68267d8770486a0ce1ef1b80"
  },
  "filename": "04_17.jpg",
  "text": "Rizid Han JAS Tenrr GFTS BAU  CPEN Ibuv IGET",
  "translated": "Riid Hand JAS Tilr GFTS BAU CPEN IGE IGE IGE",
  "image_path": "resized_04_17.jpg"
},
{
  "_id": {
    "$oid": "68267d9070486a0ce1ef1b81"
  },
  "filename": "04_18.jpg",
  "text": "Mobil 1.758 1,857 1,.957 Mobl Mart ",
  "translated": "Mobile 1,758 1,857 1, .957 MOBL MART",
  "image_path": "resized_04_18.jpg"
},
{
  "_id": {
    "$oid": "68267d9770486a0ce1ef1b82"
  },
  "filename": "04_19.jpg",
  "text": "26ina GLENOAKS UTy SALON CLEANERS & LAUNDRY CPEN Cut CLEANERS OFEN",
  "translated": "26ina GLENOAKS UTy SALON CLEANERS & LAUNDRY CPEN Cut CLEANERS OFEN",
  "image_path": "resized_04_19.jpg"
},
{
  "_id": {
    "$oid": "68267d9f70486a0ce1ef1b83"
  },
  "filename": "05_00.jpg",
  "text": "Lahwaica_ WHII White PALACE BEAKFAST dming GI GRILL UNCH CcGch ENNERS OPEN Uinsl",
  "translated": "Lahwaica_ WHII White PALACE BEAKFAST dming GI GRILL UNCH CcGch ENNERS OPEN Uinsl",
  "image_path": "resized_05_00.jpg"
},
{
  "_id": {
    "$oid": "68267da770486a0ce1ef1b84"
  },
  "filename": "05_01.jpg",
  "text": "1 Moon Palace 0",
  "translated": "1 Moon Palace 0",
  "image_path": "resized_05_01.jpg"
},
{
  "_id": {
    "$oid": "68267dae70486a0ce1ef1b85"
  },
  "filename": "05_02.jpg",
  "text": "idhite Caslle",
  "translated": "idhite Caslle",
  "image_path": "resized_05_02.jpg"
},
{
  "_id": {
    "$oid": "68267db670486a0ce1ef1b86"
  },
  "filename": "05_03.jpg",
  "text": "WOLE Taj2s",
  "translated": "I prefer ta2s",
  "image_path": "resized_05_03.jpg"
},
{
  "_id": {
    "$oid": "68267dbe70486a0ce1ef1b87"
  },
  "filename": "05_04.jpg",
  "text": "Aifitness ~fghaels EuMrt",
  "translated": "Aifitness ~fghaels EuMrt",
  "image_path": "resized_05_04.jpg"
},
{
  "_id": {
    "$oid": "68267dc570486a0ce1ef1b88"
  },
  "filename": "05_05.jpg",
  "text": "Fiskman Se3 Fine Fakcs Dze . uaparia; 6W 132",
  "translated": "Fiskman Se3 Fine Fakcs Dze . uaparia; 6W 132",
  "image_path": "resized_05_05.jpg"
},
{
  "_id": {
    "$oid": "68267dcc70486a0ce1ef1b89"
  },
  "filename": "05_06.jpg",
  "text": "- UER0 m C Ho 0L",
  "translated": "- UER0 m C Ho 0L",
  "image_path": "resized_05_06.jpg"
},
{
  "_id": {
    "$oid": "68267dd470486a0ce1ef1b8a"
  },
  "filename": "05_07.jpg",
  "text": "ata GalmeStop Boupla s",
  "translated": "The Jumusat came to BT",
  "image_path": "resized_05_07.jpg"
},
{
  "_id": {
    "$oid": "68267ddb70486a0ce1ef1b8b"
  },
  "filename": "05_08.jpg",
  "text": "GHINATOWN Hhotel 4T 01225-8888",
  "translated": "GHINATOWN Hhotel 4T 01225-8888",
  "image_path": "resized_05_08.jpg"
},
{
  "_id": {
    "$oid": "68267de470486a0ce1ef1b8c"
  },
  "filename": "05_09.jpg",
  "text": "LAIFITNESS Elliehaels MHEARTS CRAIE SIORE Eonn MARKE",
  "translated": "Laifitness Elliehaels Mhearts Craie Siore Eonn Marke",
  "image_path": "resized_05_09.jpg"
},
{
  "_id": {
    "$oid": "68267dec70486a0ce1ef1b8d"
  },
  "filename": "05_10.jpg",
  "text": "LA B2AnDStan) GRANDSTAND GRA Ddco PduI",
  "translated": "THE BIG Ddco PduI",
  "image_path": "resized_05_10.jpg"
},
{
  "_id": {
    "$oid": "68267df370486a0ce1ef1b8e"
  },
  "filename": "05_11.jpg",
  "text": "CRT 3s Martins T8nif Rar 6",
  "translated": "CRT 3S Martins T8nif Rar 6",
  "image_path": "resized_05_11.jpg"
},
{
  "_id": {
    "$oid": "68267dfa70486a0ce1ef1b8f"
  },
  "filename": "05_12.jpg",
  "text": "MXSOWIGHAUIO SERVICE 312 029 G7B: 33 Al IAu Sos",
  "translated": "MXSOWIGHAUIO SERVICE 312 029 G7B: 33 Al IAu Sos",
  "image_path": "resized_05_12.jpg"
},
{
  "_id": {
    "$oid": "68267e0370486a0ce1ef1b90"
  },
  "filename": "05_13.jpg",
  "text": "atet GalleStop",
  "translated": "atet gallestop",
  "image_path": "resized_05_13.jpg"
},
{
  "_id": {
    "$oid": "68267e0a70486a0ce1ef1b91"
  },
  "filename": "05_14.jpg",
  "text": "DE LASALLE",
  "translated": "Lasalle",
  "image_path": "resized_05_14.jpg"
},
{
  "_id": {
    "$oid": "68267e1270486a0ce1ef1b92"
  },
  "filename": "05_15.jpg",
  "text": "DE PASADA DA nTacor Tdn 4647 WTATLor 312 243 8441",
  "translated": "Of Nantacor TDN 4647 Wtatlor 312 243 8441",
  "image_path": "resized_05_15.jpg"
},
{
  "_id": {
    "$oid": "68267e1970486a0ce1ef1b93"
  },
  "filename": "05_16.jpg",
  "text": "TARGET",
  "translated": "TARGET",
  "image_path": "resized_05_16.jpg"
},
{
  "_id": {
    "$oid": "68267e2070486a0ce1ef1b94"
  },
  "filename": "05_17.jpg",
  "text": "POL~PpI",
  "translated": "Pol ~ ppi",
  "image_path": "resized_05_17.jpg"
},
{
  "_id": {
    "$oid": "68267e2770486a0ce1ef1b95"
  },
  "filename": "05_18.jpg",
  "text": "Jewel Osco",
  "translated": "Jewel Osco",
  "image_path": "resized_05_18.jpg"
},
{
  "_id": {
    "$oid": "68267e2e70486a0ce1ef1b96"
  },
  "filename": "05_19.jpg",
  "text": "10^ Twree_HAPRNNED # natat 4o t Cer",
  "translated": "10^ Twree_HAPRNNED # natat 4o t Cer",
  "image_path": "resized_05_19.jpg"
},
{
  "_id": {
    "$oid": "68267e3770486a0ce1ef1b97"
  },
  "filename": "06_00.jpg",
  "text": "FINE ITALIAN TIMMYS FRESH MEATS IMPORTS 8 DELI 8 SAUSAGES Foon STORE S1 Shot plus /5 TTALIAN ESPRESSU",
  "translated": "FINE ITALIAN TIMMYS FRESH MEATS IMPORTS 8 DELI 8 SAUSAGES Foon STORE S1 Shot plus /5 TTALIAN ESPRESSU",
  "image_path": "resized_06_00.jpg"
},
{
  "_id": {
    "$oid": "68267e4170486a0ce1ef1b98"
  },
  "filename": "06_01.jpg",
  "text": "AIRDENGAFE Gwrde\"",
  "translated": "Airdengafe gwde \"",
  "image_path": "resized_06_01.jpg"
},
{
  "_id": {
    "$oid": "68267e4a70486a0ce1ef1b99"
  },
  "filename": "06_02.jpg",
  "text": "the [924 BlueCollor Bar",
  "translated": "the [924 BlueCollor Bar",
  "image_path": "resized_06_02.jpg"
},
{
  "_id": {
    "$oid": "68267e5270486a0ce1ef1b9a"
  },
  "filename": "06_03.jpg",
  "text": "Os RAS Pd5i Sarsaa",
  "translated": "Os RAS Pd5i Sarsaa",
  "image_path": "resized_06_03.jpg"
},
{
  "_id": {
    "$oid": "68267e5b70486a0ce1ef1b9b"
  },
  "filename": "06_04.jpg",
  "text": "Jesom SAVE-WAY Fur _oR LAi BEER-WINE LOTTO PHONE CARDS",
  "translated": "Jesom SAVE-WAY Fur _oR LAi BEER-WINE LOTTO PHONE CARDS",
  "image_path": "resized_06_04.jpg"
},
{
  "_id": {
    "$oid": "68267e6670486a0ce1ef1b9c"
  },
  "filename": "06_05.jpg",
  "text": "Mars Restauranr Anthentic Vietnamtese Cadeine |",
  "translated": "Mars Restarthnra Enough WhiteNamts Cadene |",
  "image_path": "resized_06_05.jpg"
},
{
  "_id": {
    "$oid": "68267e6c70486a0ce1ef1b9d"
  },
  "filename": "06_06.jpg",
  "text": "cityplace Center East",
  "translated": "cityplace Center East",
  "image_path": "resized_06_06.jpg"
},
{
  "_id": {
    "$oid": "68267e7670486a0ce1ef1b9e"
  },
  "filename": "06_08.jpg",
  "text": "Nioin- uN LULA Bs ANTIQUE MALL Luba Es Ope Lala 8 3 URKING FREL RM dtaein",
  "translated": "Nioin-N TANGE MALEL Luba LAST Ope Ope Ope Ope Op 3 URKING FRELL RM dti",
  "image_path": "resized_06_08.jpg"
},
{
  "_id": {
    "$oid": "68267e7f70486a0ce1ef1b9f"
  },
  "filename": "06_10.jpg",
  "text": "IFTS PIFe STIFE pen",
  "translated": "IFTS PIFE STEP PEN PEN PEN",
  "image_path": "resized_06_10.jpg"
},
{
  "_id": {
    "$oid": "68267e8770486a0ce1ef1ba0"
  },
  "filename": "06_11.jpg",
  "text": "BANCKOKINN",
  "translated": "BANCKOKINN",
  "image_path": "resized_06_11.jpg"
},
{
  "_id": {
    "$oid": "68267e8f70486a0ce1ef1ba1"
  },
  "filename": "06_12.jpg",
  "text": "STARBUCKS 'corpee",
  "translated": "STARBUCKS 'corpee",
  "image_path": "resized_06_12.jpg"
},
{
  "_id": {
    "$oid": "68267e9870486a0ce1ef1ba2"
  },
  "filename": "06_13.jpg",
  "text": "STARRBUCKS CoFFEE",
  "translated": "STARRBUCKS CoFFEE",
  "image_path": "resized_06_13.jpg"
},
{
  "_id": {
    "$oid": "68267ea070486a0ce1ef1ba3"
  },
  "filename": "06_14.jpg",
  "text": "ThE LABVRINTH ~Retaoltysical Harba ~Heatne ~apoinecery E 1",
  "translated": "ThE LABVRINTH ~Retaoltysical Harba ~Heatne ~apoinecery E 1",
  "image_path": "resized_06_14.jpg"
},
{
  "_id": {
    "$oid": "68267ea870486a0ce1ef1ba4"
  },
  "filename": "06_15.jpg",
  "text": "9 DXYSURGE} DAYSURGERY",
  "translated": "9 DXYSURGE} DAYSURGERY",
  "image_path": "resized_06_15.jpg"
},
{
  "_id": {
    "$oid": "68267eb270486a0ce1ef1ba5"
  },
  "filename": "06_16.jpg",
  "text": "Mn MtrT MuH {\".'4 |  KAQuRI celulanES duror Ithtulos [ Slaaa Hcer",
  "translated": "Mn mtrt muh {\".'4 | Kaquri Celulanes Duror Ithugon [ Slaaa hcer",
  "image_path": "resized_06_16.jpg"
},
{
  "_id": {
    "$oid": "68267eb770486a0ce1ef1ba6"
  },
  "filename": "06_17.jpg",
  "text": "eim es ten cellafs 6324",
  "translated": "eim es ten cellafs 6324",
  "image_path": "resized_06_17.jpg"
},
{
  "_id": {
    "$oid": "68267ebd70486a0ce1ef1ba7"
  },
  "filename": "06_18.jpg",
  "text": "DALLAS THCOLOGICAL SCMINARY",
  "translated": "DALLAS THCOLOGICAL SCMINARY",
  "image_path": "resized_06_18.jpg"
},
{
  "_id": {
    "$oid": "68267ec470486a0ce1ef1ba8"
  },
  "filename": "07_00.jpg",
  "text": "5 Capitol Liu 00 BOOKS",
  "translated": "5 Capitol Liu 00 BOOKS",
  "image_path": "resized_07_00.jpg"
},
{
  "_id": {
    "$oid": "68267ecb70486a0ce1ef1ba9"
  },
  "filename": "07_01.jpg",
  "text": "WILLIAMS TAVERN",
  "translated": "WILLIAMS TAVERN",
  "image_path": "resized_07_01.jpg"
},
{
  "_id": {
    "$oid": "68267ed370486a0ce1ef1baa"
  },
  "filename": "07_02.jpg",
  "text": "WINBRO 16z0 GRALSL",
  "translated": "WINBRO 16z0 GRALSL",
  "image_path": "resized_07_02.jpg"
},
{
  "_id": {
    "$oid": "68267edb70486a0ce1ef1bab"
  },
  "filename": "07_03.jpg",
  "text": "420 Legta Ihe OLIN",
  "translated": "420 LETTIVATE FORM",
  "image_path": "resized_07_03.jpg"
},
{
  "_id": {
    "$oid": "68267ee270486a0ce1ef1bac"
  },
  "filename": "07_04.jpg",
  "text": "LUcKY FORTUNE RESTAURANT TAKE Out & DELIVERY 3031860-8484 No Hqur  IFaraungMearring",
  "translated": "LUcKY FORTUNE RESTAURANT TAKE Out & DELIVERY 3031860-8484 No Hqur  IFaraungMearring",
  "image_path": "resized_07_04.jpg"
},
{
  "_id": {
    "$oid": "68267ee970486a0ce1ef1bad"
  },
  "filename": "07_05.jpg",
  "text": "Domino's TL BENDERS @3thAv",
  "translated": "Domino's TL BENDERS @3thAv",
  "image_path": "resized_07_05.jpg"
},
{
  "_id": {
    "$oid": "68267ef170486a0ce1ef1bae"
  },
  "filename": "07_06.jpg",
  "text": "capitol custom Tailors foR Ladies GEniLENEN YEWEd DARERY 1 86/ 2u57 BxaGri Koor7 ATERCOL RSE Toods",
  "translated": "capitol custom Tailors foR Ladies GEniLENEN YEWEd DARERY 1 86/ 2u57 BxaGri Koor7 ATERCOL RSE Toods",
  "image_path": "resized_07_06.jpg"
},
{
  "_id": {
    "$oid": "68267ef970486a0ce1ef1baf"
  },
  "filename": "07_07.jpg",
  "text": "QUALITY FUSTom HoLLYWOOD POSTERS FRAMING \"We HAVE More Movie & Rock PosTeRS IN ONLY 6 D 8 DAYS! THAN There ARe IN THE Worldi\"",
  "translated": "QUALITY FUSTom HoLLYWOOD POSTERS FRAMING \"We HAVE More Movie & Rock PosTeRS IN ONLY 6 D 8 DAYS! THAN There ARe IN THE Worldi\"",
  "image_path": "resized_07_07.jpg"
},
{
  "_id": {
    "$oid": "68267f0070486a0ce1ef1bb0"
  },
  "filename": "07_08.jpg",
  "text": "AVENE",
  "translated": "potholes",
  "image_path": "resized_07_08.jpg"
},
{
  "_id": {
    "$oid": "68267f0870486a0ce1ef1bb1"
  },
  "filename": "07_09.jpg",
  "text": "UPTOWNVILLAGE APARIMENTS J00EZhAvE",
  "translated": "UPTOWNVILLAGE APARIMENTS J00EZhAvE",
  "image_path": "resized_07_09.jpg"
},
{
  "_id": {
    "$oid": "68267f1170486a0ce1ef1bb2"
  },
  "filename": "07_10.jpg",
  "text": "(M cDonalds Meblonsat FREE Mall Ride E Cvert Dat",
  "translated": "(M cDonalds Blue FREE Mall Ride E Cvert Dat",
  "image_path": "resized_07_10.jpg"
},
{
  "_id": {
    "$oid": "68267f1970486a0ce1ef1bb3"
  },
  "filename": "07_11.jpg",
  "text": "Nob Hill Tmn",
  "translated": "Nob Hill Tmn",
  "image_path": "resized_07_11.jpg"
},
{
  "_id": {
    "$oid": "68267f2170486a0ce1ef1bb4"
  },
  "filename": "07_12.jpg",
  "text": "JMMY IOENIS Faatatt Lionaa",
  "translated": "JMmy Yesnis Tatt Lionaa",
  "image_path": "resized_07_12.jpg"
},
{
  "_id": {
    "$oid": "68267f2970486a0ce1ef1bb5"
  },
  "filename": "07_13.jpg",
  "text": "Quiznosc SUBS Quiznosc SUBS 1275 Om) Qubu",
  "translated": "TALLS SUB TAMNS SUB 1275 ON) QUBO",
  "image_path": "resized_07_13.jpg"
},
{
  "_id": {
    "$oid": "68267f3170486a0ce1ef1bb6"
  },
  "filename": "07_14.jpg",
  "text": "BFOWN FALACZ ZOzL AND CPA Gttt Corafort INN",
  "translated": "BFOWN FALACZ ZOzL AND CPA Gttt Corafort INN",
  "image_path": "resized_07_14.jpg"
},
{
  "_id": {
    "$oid": "68267f3a70486a0ce1ef1bb7"
  },
  "filename": "07_15.jpg",
  "text": "FieStar CLEANERS W % A No (oadang UPARXINg| Qali",
  "translated": "FieStar CLEANERS W % A No (oadang UPARXINg| Qali",
  "image_path": "resized_07_15.jpg"
},
{
  "_id": {
    "$oid": "68267f4270486a0ce1ef1bb8"
  },
  "filename": "07_16.jpg",
  "text": "WAX TRAX 620 E. 13\" JRe Max Trax h Me#\"USEC ReCORDS",
  "translated": "WAX TRAX 620 E. 13\" JRe Max Trax h Me#\"USEC ReCORDS",
  "image_path": "resized_07_16.jpg"
},
{
  "_id": {
    "$oid": "68267f4a70486a0ce1ef1bb9"
  },
  "filename": "07_17.jpg",
  "text": "CHINESE FOOI CREAT WALL TEI \"()\" % 8\"52 16 1 ` FA X 6: 853 6o6 ,12",
  "translated": "CHINESE FOOI CREAT WALL TEI \"()\" % 8\"52 16 1 ` FA X 6: 853 6o6 ,12",
  "image_path": "resized_07_17.jpg"
},
{
  "_id": {
    "$oid": "68267f5270486a0ce1ef1bba"
  },
  "filename": "07_19.jpg",
  "text": "WARWICK JK HOTEL [(303) 777-7777 Yellow Cab 7228",
  "translated": "WARWICK JK HOTEL [(303) 777-7777 Yellow Cab 7228",
  "image_path": "resized_07_19.jpg"
},
{
  "_id": {
    "$oid": "68267f5b70486a0ce1ef1bbb"
  },
  "filename": "08_00.jpg",
  "text": "MSI 0od",
  "translated": "MSI 0od",
  "image_path": "resized_08_00.jpg"
},
{
  "_id": {
    "$oid": "68267f6270486a0ce1ef1bbc"
  },
  "filename": "08_01.jpg",
  "text": "00 U 5T 0 N PoLI€ E 20n DEERART MENeT",
  "translated": "00 U 5T 0 N PoLI€ E 20n DEERART MENeT",
  "image_path": "resized_08_01.jpg"
},
{
  "_id": {
    "$oid": "68267f6b70486a0ce1ef1bbd"
  },
  "filename": "08_02.jpg",
  "text": "NSTA RBUCKSCOAFEE",
  "translated": "The next rbuckscoafee",
  "image_path": "resized_08_02.jpg"
},
{
  "_id": {
    "$oid": "68267f7270486a0ce1ef1bbe"
  },
  "filename": "08_04.jpg",
  "text": "Hess| Allen Center",
  "translated": "Hess| Allen Center",
  "image_path": "resized_08_04.jpg"
},
{
  "_id": {
    "$oid": "68267f7a70486a0ce1ef1bbf"
  },
  "filename": "08_05.jpg",
  "text": "IMo ShEU PLAZA",
  "translated": "His neck is Plaza",
  "image_path": "resized_08_05.jpg"
},
{
  "_id": {
    "$oid": "68267f8170486a0ce1ef1bc0"
  },
  "filename": "08_06.jpg",
  "text": "Oad SIGnS The 4923 Oriehal JAMES CONEY ISLAND",
  "translated": "Oad SIGnS The 4923 Oriehal JAMES CONEY ISLAND",
  "image_path": "resized_08_06.jpg"
},
{
  "_id": {
    "$oid": "68267f8970486a0ce1ef1bc1"
  },
  "filename": "08_07.jpg",
  "text": "TAE MAGNOLIA",
  "translated": "TAE MAGNOLIA",
  "image_path": "resized_08_07.jpg"
},
{
  "_id": {
    "$oid": "68267f9070486a0ce1ef1bc2"
  },
  "filename": "08_08.jpg",
  "text": "MAGING ZErO'S SANDWICH SHOP",
  "translated": "Be zero's sandwich shop",
  "image_path": "resized_08_08.jpg"
},
{
  "_id": {
    "$oid": "68267f9970486a0ce1ef1bc3"
  },
  "filename": "08_09.jpg",
  "text": "{quiznos SuB",
  "translated": "{quiznos under",
  "image_path": "resized_08_09.jpg"
},
{
  "_id": {
    "$oid": "68267fa070486a0ce1ef1bc4"
  },
  "filename": "08_10.jpg",
  "text": "10 0 1 MckiN N EY",
  "translated": "10 0 1 MckiN N EY",
  "image_path": "resized_08_10.jpg"
},
{
  "_id": {
    "$oid": "68267fa770486a0ce1ef1bc5"
  },
  "filename": "08_12.jpg",
  "text": "Domino's",
  "translated": "Domino's",
  "image_path": "resized_08_12.jpg"
},
{
  "_id": {
    "$oid": "68267faf70486a0ce1ef1bc6"
  },
  "filename": "08_14.jpg",
  "text": "atet",
  "translated": "atet",
  "image_path": "resized_08_14.jpg"
},
{
  "_id": {
    "$oid": "68267fb770486a0ce1ef1bc7"
  },
  "filename": "08_15.jpg",
  "text": "FOuk SEASONS HOTEI",
  "translated": "To be the folk sessions",
  "image_path": "resized_08_15.jpg"
},
{
  "_id": {
    "$oid": "68267fbe70486a0ce1ef1bc8"
  },
  "filename": "08_16.jpg",
  "text": "ALDEN",
  "translated": "ALDEN",
  "image_path": "resized_08_16.jpg"
},
{
  "_id": {
    "$oid": "68267fc670486a0ce1ef1bc9"
  },
  "filename": "08_17.jpg",
  "text": "SPAGHETTI WAREHOUSE 1 1",
  "translated": "SPAGHETTI WAREHOUSE 1 1",
  "image_path": "resized_08_17.jpg"
},
{
  "_id": {
    "$oid": "68267fce70486a0ce1ef1bca"
  },
  "filename": "08_18.jpg",
  "text": "C Jula",
  "translated": "C Jula",
  "image_path": "resized_08_18.jpg"
},
{
  "_id": {
    "$oid": "68267fd470486a0ce1ef1bcb"
  },
  "filename": "08_19.jpg",
  "text": "fnce/s",
  "translated": "fnce/s",
  "image_path": "resized_08_19.jpg"
},
{
  "_id": {
    "$oid": "68267fda70486a0ce1ef1bcc"
  },
  "filename": "09_00.jpg",
  "text": "CIRCLE CENTRE",
  "translated": "CIRCLE CENTRE",
  "image_path": "resized_09_00.jpg"
},
{
  "_id": {
    "$oid": "68267fe170486a0ce1ef1bcd"
  },
  "filename": "09_01.jpg",
  "text": "M U R p Hx",
  "translated": "M U R p Hx",
  "image_path": "resized_09_01.jpg"
},
{
  "_id": {
    "$oid": "68267fe770486a0ce1ef1bce"
  },
  "filename": "09_02.jpg",
  "text": "St} DAVS IWI' New Jersey",
  "translated": "St} DAVS IWI' New Jersey",
  "image_path": "resized_09_02.jpg"
},
{
  "_id": {
    "$oid": "68267fed70486a0ce1ef1bcf"
  },
  "filename": "09_03.jpg",
  "text": "HOULIHA HOULIHAN'S",
  "translated": "HOULIHA HOULIHAN'S",
  "image_path": "resized_09_03.jpg"
},
{
  "_id": {
    "$oid": "68267ff370486a0ce1ef1bd0"
  },
  "filename": "09_04.jpg",
  "text": "Stgals h Seel",
  "translated": "Stgals h Seel",
  "image_path": "resized_09_04.jpg"
},
{
  "_id": {
    "$oid": "68267ff970486a0ce1ef1bd1"
  },
  "filename": "09_05.jpg",
  "text": "complexions",
  "translated": "complexions",
  "image_path": "resized_09_05.jpg"
},
{
  "_id": {
    "$oid": "68267fff70486a0ce1ef1bd2"
  },
  "filename": "09_06.jpg",
  "text": "'PENNSY LVAMIAs > zdoGal E LIVING ROOM LOUNGE | nle Y LI",
  "translated": "'PENNSY LVAMIAs > zdoGal E LIVING ROOM LOUNGE | nle Y LI",
  "image_path": "resized_09_06.jpg"
},
{
  "_id": {
    "$oid": "6826800770486a0ce1ef1bd3"
  },
  "filename": "09_07.jpg",
  "text": "Tudiaua Hcer! IAI Hepertory 'Thente Fel",
  "translated": "Tudiaua Hcer!Iai Hepertory 'Thente Fellow",
  "image_path": "resized_09_07.jpg"
},
{
  "_id": {
    "$oid": "6826800d70486a0ce1ef1bd4"
  },
  "filename": "09_08.jpg",
  "text": "WASHINGTON Ivlio Aschool",
  "translated": "WASHINGTON Ivlio Aschool",
  "image_path": "resized_09_08.jpg"
},
{
  "_id": {
    "$oid": "6826801370486a0ce1ef1bd5"
  },
  "filename": "09_09.jpg",
  "text": "THERAPY NighTcLUM & |tnG",
  "translated": "THERAPY NighTcLUM & |tnG",
  "image_path": "resized_09_09.jpg"
},
{
  "_id": {
    "$oid": "6826801a70486a0ce1ef1bd6"
  },
  "filename": "09_10.jpg",
  "text": "LEGA S",
  "translated": "Legal",
  "image_path": "resized_09_10.jpg"
},
{
  "_id": {
    "$oid": "6826802070486a0ce1ef1bd7"
  },
  "filename": "09_11.jpg",
  "text": "B CHASE TOWER CRAsEo",
  "translated": "B CHASE TOWER CRAsEo",
  "image_path": "resized_09_11.jpg"
},
{
  "_id": {
    "$oid": "6826802770486a0ce1ef1bd8"
  },
  "filename": "09_12.jpg",
  "text": "WHEELER MTSSToN MINISTRIES",
  "translated": "WHEELER MTSSToN MINISTRIES",
  "image_path": "resized_09_12.jpg"
},
{
  "_id": {
    "$oid": "6826802d70486a0ce1ef1bd9"
  },
  "filename": "09_13.jpg",
  "text": "JOBSITE SUPPLY comstrectidh IdE.s R7 Work 684-7474",
  "translated": "JOBSITE SUPPLY comstrectidh IdE.s R7 Work 684-7474",
  "image_path": "resized_09_13.jpg"
},
{
  "_id": {
    "$oid": "6826803370486a0ce1ef1bda"
  },
  "filename": "09_14.jpg",
  "text": "ZOLLIZESCO Dtaino producis",
  "translated": "ZOLLIZESCO Dtaino producis",
  "image_path": "resized_09_14.jpg"
},
{
  "_id": {
    "$oid": "6826803970486a0ce1ef1bdb"
  },
  "filename": "09_15.jpg",
  "text": "herattone",
  "translated": "herattone",
  "image_path": "resized_09_15.jpg"
},
{
  "_id": {
    "$oid": "6826803f70486a0ce1ef1bdc"
  },
  "filename": "09_16.jpg",
  "text": "INDUSTRIaL Anodizing 1610]",
  "translated": "INDUSTRIaL Anodizing 1610]",
  "image_path": "resized_09_16.jpg"
},
{
  "_id": {
    "$oid": "6826804570486a0ce1ef1bdd"
  },
  "filename": "09_17.jpg",
  "text": "CROWNE PLAZA Motel$ R E $ 0 R T $ THE GRAND HALL AND CONFERENCE CENTER",
  "translated": "CROWNE PLAZA Motel$ R E $ 0 R T $ THE GRAND HALL AND CONFERENCE CENTER",
  "image_path": "resized_09_17.jpg"
},
{
  "_id": {
    "$oid": "6826804b70486a0ce1ef1bde"
  },
  "filename": "09_18.jpg",
  "text": "HOMEWOOD SUITES",
  "translated": "HOMEWOOD SUITES",
  "image_path": "resized_09_18.jpg"
},
{
  "_id": {
    "$oid": "6826805170486a0ce1ef1bdf"
  },
  "filename": "09_19.jpg",
  "text": "SIMON",
  "translated": "SIMON",
  "image_path": "resized_09_19.jpg"
},
{
  "_id": {
    "$oid": "6826805870486a0ce1ef1be0"
  },
  "filename": "10_02.jpg",
  "text": "DUNKINDONUIS Phc Oift",
  "translated": "Dunkindonuis Phc Oift",
  "image_path": "resized_10_02.jpg"
},
{
  "_id": {
    "$oid": "6826805d70486a0ce1ef1be1"
  },
  "filename": "10_03.jpg",
  "text": "Raya PAKISTAN TEA HOUSE} A Touch of 'Traditional Cuisine TEX MILYICAN Eonrss 176 churrch St 212-240-9800 PA n G OPE\" 163",
  "translated": "Raya PAKISTAN TEA HOUSE} A Touch of 'Traditional Cuisine TEX MILYICAN Eonrss 176 churrch St 212-240-9800 PA n G OPE\" 163",
  "image_path": "resized_10_03.jpg"
},
{
  "_id": {
    "$oid": "6826806370486a0ce1ef1be2"
  },
  "filename": "10_04.jpg",
  "text": "En Box\" (mo   STANDING Fifth Ave AnyTIME LENSCRAFTERS H1oam-6pw] MON-FrI Jc LC 'BLock  The \" EINE+2POINTS ",
  "translated": "En Box\" (mo   STANDING Fifth Ave AnyTIME LENSCRAFTERS H1oam-6pw] MON-FrI Jc LC 'BLock  The \" EINE+2POINTS",
  "image_path": "resized_10_04.jpg"
},
{
  "_id": {
    "$oid": "6826806870486a0ce1ef1be3"
  },
  "filename": "10_05.jpg",
  "text": "5059 Fossil FossL FoS FiSSIL",
  "translated": "5059 Fossil FossL FoS FiSSIL",
  "image_path": "resized_10_05.jpg"
},
{
  "_id": {
    "$oid": "6826806e70486a0ce1ef1be4"
  },
  "filename": "10_17.jpg",
  "text": "JeanLouls Devid CUT 26",
  "translated": "JeanLouls Devid CUT 26",
  "image_path": "resized_10_17.jpg"
},
{
  "_id": {
    "$oid": "6826807370486a0ce1ef1be5"
  },
  "filename": "10_18.jpg",
  "text": "FranklWines Ko StandinG ucPt @ucts BAM-7PM ciet",
  "translated": "FranklWines Ko StandinG ucPt @ucts BAM-7PM ciet",
  "image_path": "resized_10_18.jpg"
},
{
  "_id": {
    "$oid": "6826807970486a0ce1ef1be6"
  },
  "filename": "11_00.jpg",
  "text": "GRAND BOHEMIAN HOTEL ENTRANCE",
  "translated": "GRAND BOHEMIAN HOTEL ENTRANCE",
  "image_path": "resized_11_00.jpg"
},
{
  "_id": {
    "$oid": "6826808070486a0ce1ef1be7"
  },
  "filename": "11_01.jpg",
  "text": "( NAPASORN L",
  "translated": "(Napasorn l",
  "image_path": "resized_11_01.jpg"
},
{
  "_id": {
    "$oid": "6826808870486a0ce1ef1be8"
  },
  "filename": "11_02.jpg",
  "text": "Ii HATSU SUSH",
  "translated": "Good first SH",
  "image_path": "resized_11_02.jpg"
},
{
  "_id": {
    "$oid": "6826808e70486a0ce1ef1be9"
  },
  "filename": "11_03.jpg",
  "text": "AL'S ARMY STORE 1957 EST",
  "translated": "AL'S ARMY STORE 1957 EST",
  "image_path": "resized_11_03.jpg"
},
{
  "_id": {
    "$oid": "6826809670486a0ce1ef1bea"
  },
  "filename": "11_04.jpg",
  "text": "OrkndoSentinel ualeatlons",
  "translated": "Orkndosentinel ualeatlons",
  "image_path": "resized_11_04.jpg"
},
{
  "_id": {
    "$oid": "6826809c70486a0ce1ef1beb"
  },
  "filename": "11_05.jpg",
  "text": "2009 Guodl KUP a DELIVERY ZES BI SHOP 0071228*7088 recials 02009 Google",
  "translated": "2009 Guodl KUP a DELIVERY ZES BI SHOP 0071228*7088 recials 02009 Google",
  "image_path": "resized_11_05.jpg"
},
{
  "_id": {
    "$oid": "682680a270486a0ce1ef1bec"
  },
  "filename": "11_06.jpg",
  "text": "STARBUCKS COFFEE",
  "translated": "STARBUCKS COFFEE",
  "image_path": "resized_11_06.jpg"
},
{
  "_id": {
    "$oid": "682680a970486a0ce1ef1bed"
  },
  "filename": "11_07.jpg",
  "text": "Porlioment Huuse RESORT LATIA Nicht LISA LANE DJEDIDO",
  "translated": "Parliament house resort latia not lisa lane djedidi",
  "image_path": "resized_11_07.jpg"
},
{
  "_id": {
    "$oid": "682680af70486a0ce1ef1bee"
  },
  "filename": "11_08.jpg",
  "text": "COLONIAL RESTAURANT LOUNGE at",
  "translated": "COLONIAL RESTAURANT LOUNGE at",
  "image_path": "resized_11_08.jpg"
},
{
  "_id": {
    "$oid": "682680b670486a0ce1ef1bef"
  },
  "filename": "11_09.jpg",
  "text": "CENMRAL Sualon BAR BENTRAL STATION BAR I00 EAST Rhone] ",
  "translated": "CENMRAL Sualon BAR BENTRAL STATION BAR I00 EAST Rhone]",
  "image_path": "resized_11_09.jpg"
},
{
  "_id": {
    "$oid": "682680be70486a0ce1ef1bf0"
  },
  "filename": "11_10.jpg",
  "text": "'CHURCH OF SCIENTOLOGY 02009 Goot ~hubbard DANETICS coundanon  00 _ 2009 (oogle:",
  "translated": "'Church of Scientology 02009 GOT ~HUBBARD Danetics County 00 _ 2009 (Oogle:",
  "image_path": "resized_11_10.jpg"
},
{
  "_id": {
    "$oid": "682680c770486a0ce1ef1bf1"
  },
  "filename": "11_11.jpg",
  "text": "MAYOR BOB CARR PERFORMING ARTS CENTRE ORLANDO PHI HARMONIC PRESENITS E Zrka TE dlxa SAT, Hov PM & 8 F4",
  "translated": "MAYOR BOB CARR PRESENITS",
  "image_path": "resized_11_11.jpg"
},
{
  "_id": {
    "$oid": "682680cf70486a0ce1ef1bf2"
  },
  "filename": "11_12.jpg",
  "text": "'IZOU TiJuANA_ FLATS ZOUZOU 2",
  "translated": "'Isu Taxoa_ Flaz Zouzu 2",
  "image_path": "resized_11_12.jpg"
},
{
  "_id": {
    "$oid": "682680d570486a0ce1ef1bf3"
  },
  "filename": "11_13.jpg",
  "text": "7F; DONG - A-SUPERMARKET",
  "translated": "7F; DONG - A-SUPERMARKET",
  "image_path": "resized_11_13.jpg"
},
{
  "_id": {
    "$oid": "682680db70486a0ce1ef1bf4"
  },
  "filename": "11_14.jpg",
  "text": "DETROT IOE$ ORIGINNAGCONEY ISLAND RESTAURANT Security 40I",
  "translated": "DETROT IOE$ ORIGINNAGCONEY ISLAND RESTAURANT Security 40I",
  "image_path": "resized_11_14.jpg"
},
{
  "_id": {
    "$oid": "682680e170486a0ce1ef1bf5"
  },
  "filename": "11_15.jpg",
  "text": "CoConiaC PhOTO & HOBBY INC",
  "translated": "CoConiaC PhOTO & HOBBY INC",
  "image_path": "resized_11_15.jpg"
},
{
  "_id": {
    "$oid": "682680e870486a0ce1ef1bf6"
  },
  "filename": "11_16.jpg",
  "text": "AseeeSHGON",
  "translated": "Aseheshgon",
  "image_path": "resized_11_16.jpg"
},
{
  "_id": {
    "$oid": "682680ee70486a0ce1ef1bf7"
  },
  "filename": "11_17.jpg",
  "text": "Fjun @h Tqbu",
  "translated": "Fjun @h Tqbu",
  "image_path": "resized_11_17.jpg"
},
{
  "_id": {
    "$oid": "682680f570486a0ce1ef1bf8"
  },
  "filename": "11_18.jpg",
  "text": "ROO cityartsfactory OPEN DO Not Emer",
  "translated": "ROO cityartsfactory OPEN DO Not Emer",
  "image_path": "resized_11_18.jpg"
},
{
  "_id": {
    "$oid": "682680fb70486a0ce1ef1bf9"
  },
  "filename": "11_19.jpg",
  "text": "ALLNEWROOMS ALL RoOMS S47.95 101808 Inrv 12j008 Travelodge '",
  "translated": "ALLNEWROOMS ALL RoOMS S47.95 101808 Inrv 12j008 Travelodge '",
  "image_path": "resized_11_19.jpg"
},
{
  "_id": {
    "$oid": "6826810170486a0ce1ef1bfa"
  },
  "filename": "12_02.jpg",
  "text": ". ' _t ID Bank 9 Wont PICDAY NY \"7886 | DAY WERE OPENI FREET",
  "translated": ". ' _t ID Bank 9 Wont PICDAY NY \"7886 | DAY WERE OPENI FREET",
  "image_path": "resized_12_02.jpg"
},
{
  "_id": {
    "$oid": "6826810670486a0ce1ef1bfb"
  },
  "filename": "12_03.jpg",
  "text": "Hard Rock CAE ard Tec",
  "translated": "Hard Rock CAE ard Tec",
  "image_path": "resized_12_03.jpg"
},
{
  "_id": {
    "$oid": "6826810c70486a0ce1ef1bfc"
  },
  "filename": "12_04.jpg",
  "text": "LMBASSY SUITES Center City PARKING DO NOT ENTIR #ENTER !",
  "translated": "LMBASSY SUITES Center City PARKING DO NOT ENTIR #ENTER !",
  "image_path": "resized_12_04.jpg"
},
{
  "_id": {
    "$oid": "6826811170486a0ce1ef1bfd"
  },
  "filename": "12_05.jpg",
  "text": "⚠️ No text found.",
  "translated": "⚠️ No text found.",
  "image_path": "resized_12_05.jpg"
},
{
  "_id": {
    "$oid": "6826811770486a0ce1ef1bfe"
  },
  "filename": "12_06.jpg",
  "text": "6 a P G I R 0 G E L 4 T 0 ;%\" ! ; Panine Gelato Gelato",
  "translated": "6 a P G I R 0 G E L 4 T 0;%\"!; Panine ice cream ice cream",
  "image_path": "resized_12_06.jpg"
},
{
  "_id": {
    "$oid": "6826811c70486a0ce1ef1bff"
  },
  "filename": "12_07.jpg",
  "text": "THE WINDSOR OnaniAann Atnatn",
  "translated": "THE WINDSOR OnaniAann Atnatn",
  "image_path": "resized_12_07.jpg"
},
{
  "_id": {
    "$oid": "6826812270486a0ce1ef1c00"
  },
  "filename": "12_08.jpg",
  "text": "Sheraton Uhilling SEAFOOD HERRAC RESTAURANT LOBBY BAR",
  "translated": "Sheraton Uhilling SEAFOOD HERRAC RESTAURANT LOBBY BAR",
  "image_path": "resized_12_08.jpg"
},
{
  "_id": {
    "$oid": "6826812770486a0ce1ef1c01"
  },
  "filename": "12_09.jpg",
  "text": "~DER JoE S",
  "translated": "~ The Joe S",
  "image_path": "resized_12_09.jpg"
},
{
  "_id": {
    "$oid": "6826812e70486a0ce1ef1c02"
  },
  "filename": "12_10.jpg",
  "text": "PrEssioN PAR@ BTERES",
  "translated": "Pressure by@ bteres",
  "image_path": "resized_12_10.jpg"
},
{
  "_id": {
    "$oid": "6826813470486a0ce1ef1c03"
  },
  "filename": "12_11.jpg",
  "text": "28 BELLA VIST NC FuU",
  "translated": "28 BELLA VIST NC FU",
  "image_path": "resized_12_11.jpg"
},
{
  "_id": {
    "$oid": "6826813a70486a0ce1ef1c04"
  },
  "filename": "12_13.jpg",
  "text": "8a 755 E CHERRY StREET Kcuft#gy KoshI 2 VEGETARIAN RESTAUR Xf 4010 CHERRY STREET Tel:215-923- Alaaea N",
  "translated": "8a 755 E CHERRY StREET Kcuft#gy KoshI 2 VEGETARIAN RESTAUR Xf 4010 CHERRY STREET Tel:215-923- Alaaea N",
  "image_path": "resized_12_13.jpg"
},
{
  "_id": {
    "$oid": "6826814170486a0ce1ef1c05"
  },
  "filename": "12_15.jpg",
  "text": "OJjebs",
  "translated": "Ojjebs",
  "image_path": "resized_12_15.jpg"
},
{
  "_id": {
    "$oid": "6826814670486a0ce1ef1c06"
  },
  "filename": "12_16.jpg",
  "text": "UNITBD ETATET Maint 80s LHILL M nng eciuy",
  "translated": "UNITBD ETATET Maint 80s LHILL M nng eciuy",
  "image_path": "resized_12_16.jpg"
},
{
  "_id": {
    "$oid": "6826814c70486a0ce1ef1c07"
  },
  "filename": "12_18.jpg",
  "text": "05 Vedicint CainaTOwN DollaR_Inc 4 S18 & UP 27-220 Vtotan Hottttid ibtiaay #ult Lot In WIG o",
  "translated": "05 Vedicint CainaTOwN DollaR_Inc 4 S18 & UP 27-220 Vtotan Hottttid ibtiaay #ult Lot In WIG o",
  "image_path": "resized_12_18.jpg"
},
{
  "_id": {
    "$oid": "6826815270486a0ce1ef1c08"
  },
  "filename": "12_19.jpg",
  "text": "PLAYS AND PLAYERS \"'\"",
  "translated": "PLAYS AND PLAYERS \"'\"",
  "image_path": "resized_12_19.jpg"
},
{
  "_id": {
    "$oid": "6826815770486a0ce1ef1c09"
  },
  "filename": "13_01.jpg",
  "text": "UNIVERSITY € ENTER",
  "translated": "UNIVERSITY € ENTER",
  "image_path": "resized_13_01.jpg"
},
{
  "_id": {
    "$oid": "6826815c70486a0ce1ef1c0a"
  },
  "filename": "13_02.jpg",
  "text": "Prbueks]coFfee",
  "translated": "Prbueks]coFfee",
  "image_path": "resized_13_02.jpg"
},
{
  "_id": {
    "$oid": "6826816270486a0ce1ef1c0b"
  },
  "filename": "13_03.jpg",
  "text": "Cafe Rontd Ptzza Pasta Saluda 4 QUUnOSSuB Soua",
  "translated": "Cafe rond pizza pasta saluda 4 quuno sub soy",
  "image_path": "resized_13_03.jpg"
},
{
  "_id": {
    "$oid": "6826816870486a0ce1ef1c0c"
  },
  "filename": "13_04.jpg",
  "text": "JeLkS DopGutow",
  "translated": "JeLkS DopGutow",
  "image_path": "resized_13_04.jpg"
},
{
  "_id": {
    "$oid": "6826816e70486a0ce1ef1c0d"
  },
  "filename": "13_05.jpg",
  "text": "ELPORTAL",
  "translated": "Proportal",
  "image_path": "resized_13_05.jpg"
},
{
  "_id": {
    "$oid": "6826817370486a0ce1ef1c0e"
  },
  "filename": "13_07.jpg",
  "text": "eye lounge",
  "translated": "eye lounge",
  "image_path": "resized_13_07.jpg"
},
{
  "_id": {
    "$oid": "6826817a70486a0ce1ef1c0f"
  },
  "filename": "13_08.jpg",
  "text": "JEnterprise",
  "translated": "Girls prize",
  "image_path": "resized_13_08.jpg"
},
{
  "_id": {
    "$oid": "6826818170486a0ce1ef1c10"
  },
  "filename": "13_09.jpg",
  "text": "Yasda Bento",
  "translated": "Yasda Bento",
  "image_path": "resized_13_09.jpg"
},
{
  "_id": {
    "$oid": "6826818770486a0ce1ef1c11"
  },
  "filename": "13_10.jpg",
  "text": "pizzahvt",
  "translated": "pizzahvt",
  "image_path": "resized_13_10.jpg"
},
{
  "_id": {
    "$oid": "6826818d70486a0ce1ef1c12"
  },
  "filename": "13_11.jpg",
  "text": "MAGIC AUTO a",
  "translated": "MAGIC AUTO a",
  "image_path": "resized_13_11.jpg"
},
{
  "_id": {
    "$oid": "6826819270486a0ce1ef1c13"
  },
  "filename": "13_12.jpg",
  "text": "JCA",
  "translated": "JCA",
  "image_path": "resized_13_12.jpg"
},
{
  "_id": {
    "$oid": "6826819770486a0ce1ef1c14"
  },
  "filename": "13_13.jpg",
  "text": "Epex LH",
  "translated": "Epex LH",
  "image_path": "resized_13_13.jpg"
},
{
  "_id": {
    "$oid": "6826819d70486a0ce1ef1c15"
  },
  "filename": "13_14.jpg",
  "text": "cicles:dscsatopes",
  "translated": "Cycles: DSCSATOPES",
  "image_path": "resized_13_14.jpg"
},
{
  "_id": {
    "$oid": "682681a470486a0ce1ef1c16"
  },
  "filename": "13_15.jpg",
  "text": "WNDHIAM Kl ",
  "translated": "Wndhiam kl",
  "image_path": "resized_13_15.jpg"
},
{
  "_id": {
    "$oid": "682681a970486a0ce1ef1c17"
  },
  "filename": "13_16.jpg",
  "text": "modified arts",
  "translated": "modified arts",
  "image_path": "resized_13_16.jpg"
},
{
  "_id": {
    "$oid": "682681ae70486a0ce1ef1c18"
  },
  "filename": "13_17.jpg",
  "text": "ATWAYS e4444/ FEu S",
  "translated": "ATWAYS e4444/ FEu S",
  "image_path": "resized_13_17.jpg"
},
{
  "_id": {
    "$oid": "682681b570486a0ce1ef1c19"
  },
  "filename": "13_18.jpg",
  "text": "PORTLAND$ Testauro bar",
  "translated": "Portland $ TestauRo Bar",
  "image_path": "resized_13_18.jpg"
},
{
  "_id": {
    "$oid": "682681bb70486a0ce1ef1c1a"
  },
  "filename": "13_19.jpg",
  "text": "C H€UN RoNT CHEUVRONT RESTAURANT",
  "translated": "C € a ront cheuvront restaurant",
  "image_path": "resized_13_19.jpg"
},
{
  "_id": {
    "$oid": "682681c370486a0ce1ef1c1b"
  },
  "filename": "14_00.jpg",
  "text": "3  PCE PaEL PARK PG E",
  "translated": "3 pce pel Park pg to",
  "image_path": "resized_14_00.jpg"
},
{
  "_id": {
    "$oid": "682681ca70486a0ce1ef1c1c"
  },
  "filename": "14_01.jpg",
  "text": "ATG GINS",
  "translated": "ATG GINS",
  "image_path": "resized_14_01.jpg"
},
{
  "_id": {
    "$oid": "682681d170486a0ce1ef1c1d"
  },
  "filename": "14_02.jpg",
  "text": "Martioil",
  "translated": "Martioil",
  "image_path": "resized_14_02.jpg"
},
{
  "_id": {
    "$oid": "682681d770486a0ce1ef1c1e"
  },
  "filename": "14_03.jpg",
  "text": "Living ROOm ThEATERS",
  "translated": "Living ROOm ThEATERS",
  "image_path": "resized_14_03.jpg"
},
{
  "_id": {
    "$oid": "682681de70486a0ce1ef1c1f"
  },
  "filename": "14_04.jpg",
  "text": "%0 STANDARD INSURANCE CENTER 900 S,W:   FIFTH AVENUE",
  "translated": "%0 STANDARD INSURANCE CENTER 900 S,W:   FIFTH AVENUE",
  "image_path": "resized_14_04.jpg"
},
{
  "_id": {
    "$oid": "682681e570486a0ce1ef1c20"
  },
  "filename": "14_05.jpg",
  "text": "Roots",
  "translated": "Roots",
  "image_path": "resized_14_05.jpg"
},
{
  "_id": {
    "$oid": "682681eb70486a0ce1ef1c21"
  },
  "filename": "14_06.jpg",
  "text": "Convention Center",
  "translated": "Convention Center",
  "image_path": "resized_14_06.jpg"
},
{
  "_id": {
    "$oid": "682681f370486a0ce1ef1c22"
  },
  "filename": "14_07.jpg",
  "text": "EvEREST COLLEGE",
  "translated": "EvEREST COLLEGE",
  "image_path": "resized_14_07.jpg"
},
{
  "_id": {
    "$oid": "682681f970486a0ce1ef1c23"
  },
  "filename": "14_08.jpg",
  "text": "PIONEER PLACE SSIMWVENUL",
  "translated": "PIONEER PLACE SSIMWVENUL",
  "image_path": "resized_14_08.jpg"
},
{
  "_id": {
    "$oid": "6826820070486a0ce1ef1c24"
  },
  "filename": "14_09.jpg",
  "text": "Cinema 2| STEVE DUSCEMI'S INTERVIEN IEXT: NOLEAD InisIgHT'",
  "translated": "Cinema 2| STEVE DUSCEMI'S INTERVIEN IEXT: NOLEAD InisIgHT'",
  "image_path": "resized_14_09.jpg"
},
{
  "_id": {
    "$oid": "6826820670486a0ce1ef1c25"
  },
  "filename": "14_10.jpg",
  "text": "Pa KitL-",
  "translated": "Pa KitL-",
  "image_path": "resized_14_10.jpg"
},
{
  "_id": {
    "$oid": "6826820d70486a0ce1ef1c26"
  },
  "filename": "14_11.jpg",
  "text": "V2}Quiuoon St0r2 @St Quioon Si0ne)",
  "translated": "V2}Quiuoon St0r2 @St Quioon Si0ne)",
  "image_path": "resized_14_11.jpg"
},
{
  "_id": {
    "$oid": "6826821470486a0ce1ef1c27"
  },
  "filename": "14_12.jpg",
  "text": "DAN & LOUIS B 0a S6",
  "translated": "Dan & louis b 0a s6",
  "image_path": "resized_14_12.jpg"
},
{
  "_id": {
    "$oid": "6826821c70486a0ce1ef1c28"
  },
  "filename": "14_13.jpg",
  "text": "Qission cbeater Pab",
  "translated": "Lowsion Cbeater Help",
  "image_path": "resized_14_13.jpg"
},
{
  "_id": {
    "$oid": "6826822470486a0ce1ef1c29"
  },
  "filename": "14_14.jpg",
  "text": "SATYRICONPDXCOMI THELLIFEANDITIMES SYSTEM ANDI STAKIOH MICROIIA",
  "translated": "SatyriconPDXComi Thellifeanditimes System Andi Stakioh microiia",
  "image_path": "resized_14_14.jpg"
},
{
  "_id": {
    "$oid": "6826822a70486a0ce1ef1c2a"
  },
  "filename": "14_15.jpg",
  "text": "Genies",
  "translated": "Genies",
  "image_path": "resized_14_15.jpg"
},
{
  "_id": {
    "$oid": "6826823170486a0ce1ef1c2b"
  },
  "filename": "14_16.jpg",
  "text": "E M EVERYDAY Music ]",
  "translated": "E M EVERYDAY Music ]",
  "image_path": "resized_14_16.jpg"
},
{
  "_id": {
    "$oid": "6826823770486a0ce1ef1c2c"
  },
  "filename": "14_17.jpg",
  "text": "Lincom rich Icp - 1",
  "translated": "Lincom rich Icp - 1",
  "image_path": "resized_14_17.jpg"
},
{
  "_id": {
    "$oid": "6826823e70486a0ce1ef1c2d"
  },
  "filename": "14_18.jpg",
  "text": "Marrlatt Maroll",
  "translated": "Marrlatt Maroll",
  "image_path": "resized_14_18.jpg"
},
{
  "_id": {
    "$oid": "6826824470486a0ce1ef1c2e"
  },
  "filename": "14_19.jpg",
  "text": "HUcKY LaBracor LREW PUB",
  "translated": "HUcKY LaBracor LREW PUB",
  "image_path": "resized_14_19.jpg"
},
{
  "_id": {
    "$oid": "6826824b70486a0ce1ef1c2f"
  },
  "filename": "15_01.jpg",
  "text": "EMBASSY SUITES PARKING",
  "translated": "EMBASSY SUITES PARKING",
  "image_path": "resized_15_01.jpg"
},
{
  "_id": {
    "$oid": "6826825170486a0ce1ef1c30"
  },
  "filename": "15_02.jpg",
  "text": "Yard House SELECTION OF GREAT FOOD CLASSIC Rock WORLD'S \"BEER 'DRAFTI LARGEST",
  "translated": "Yard House SELECTION OF GREAT FOOD CLASSIC Rock WORLD'S \"BEER 'DRAFTI LARGEST",
  "image_path": "resized_15_02.jpg"
},
{
  "_id": {
    "$oid": "6826825870486a0ce1ef1c31"
  },
  "filename": "15_03.jpg",
  "text": "JaI DIEGo HAQDOL EICUESIOR Edn com 3101012844111 2009 Google Qw",
  "translated": "JaI DIEGo HAQDOL EICUESIOR Edn com 3101012844111 2009 Google Qw",
  "image_path": "resized_15_03.jpg"
},
{
  "_id": {
    "$oid": "6826826070486a0ce1ef1c32"
  },
  "filename": "15_04.jpg",
  "text": "Timken Muscum ofArt I500 @ a Work. Ofan Ewropnnan WotkaOfA5\" And Kuaetan Icona Dong G",
  "translated": "Tikkken muscum officials i500 @ a work.Ofan ewropnnan wotkaofa5\" and etry Icon Dong g",
  "image_path": "resized_15_04.jpg"
},
{
  "_id": {
    "$oid": "6826826670486a0ce1ef1c33"
  },
  "filename": "15_05.jpg",
  "text": "Sn Dlego Automotive Museum ONLY",
  "translated": "Sn Dlego Automotive Museum ONLY",
  "image_path": "resized_15_05.jpg"
},
{
  "_id": {
    "$oid": "6826826d70486a0ce1ef1c34"
  },
  "filename": "15_06.jpg",
  "text": "BL CORTEZ",
  "translated": "Bl Cortez",
  "image_path": "resized_15_06.jpg"
},
{
  "_id": {
    "$oid": "6826827270486a0ce1ef1c35"
  },
  "filename": "15_07.jpg",
  "text": "CROCES  RESTAURANT",
  "translated": "CROCES  RESTAURANT",
  "image_path": "resized_15_07.jpg"
},
{
  "_id": {
    "$oid": "6826827a70486a0ce1ef1c36"
  },
  "filename": "15_08.jpg",
  "text": "The (sbah",
  "translated": "W (morning",
  "image_path": "resized_15_08.jpg"
},
{
  "_id": {
    "$oid": "6826828270486a0ce1ef1c37"
  },
  "filename": "15_09.jpg",
  "text": "BAYSIDE Rest Mestern INn",
  "translated": "Bayside Rest Master in",
  "image_path": "resized_15_09.jpg"
},
{
  "_id": {
    "$oid": "6826828870486a0ce1ef1c38"
  },
  "filename": "15_10.jpg",
  "text": "AIR & SPACE MUSEUM",
  "translated": "AIR & SPACE MUSEUM",
  "image_path": "resized_15_10.jpg"
},
{
  "_id": {
    "$oid": "6826829070486a0ce1ef1c39"
  },
  "filename": "15_11.jpg",
  "text": "AMERISA ELAZL \"uking Intra e #0\" ( lesrace Hit Onl; Do Nol Int",
  "translated": "AMERISA ELAZL \"uking Intra e #0\" ( lesrace Hit Onl; Do Nol Int",
  "image_path": "resized_15_11.jpg"
},
{
  "_id": {
    "$oid": "6826829670486a0ce1ef1c3a"
  },
  "filename": "15_12.jpg",
  "text": "HORTON GRAND HOTEL",
  "translated": "HORTON GRAND HOTEL",
  "image_path": "resized_15_12.jpg"
},
{
  "_id": {
    "$oid": "6826829e70486a0ce1ef1c3b"
  },
  "filename": "15_13.jpg",
  "text": "aISEUM 0F:Mant",
  "translated": "0F e aiseum: mant",
  "image_path": "resized_15_13.jpg"
},
{
  "_id": {
    "$oid": "682682a670486a0ce1ef1c3c"
  },
  "filename": "15_14.jpg",
  "text": "Comifot JiNv Comfort INN 660 G Street 1-800-598-1810 Gaslamp",
  "translated": "Comifot JinV Comfort in 660 g street 1-800-598-1810 Gaslamp",
  "image_path": "resized_15_14.jpg"
},
{
  "_id": {
    "$oid": "682682ab70486a0ce1ef1c3d"
  },
  "filename": "15_15.jpg",
  "text": "GHIRARDELLI CE CREAM CHOCOLATE SHL AND",
  "translated": "GHIRARDELLI CE CREAM CHOCOLATE SHL AND",
  "image_path": "resized_15_15.jpg"
},
{
  "_id": {
    "$oid": "682682b270486a0ce1ef1c3e"
  },
  "filename": "15_16.jpg",
  "text": "SAN DIFGO CONVENTION CENTER",
  "translated": "SAN DIFGO CONVENTION CENTER",
  "image_path": "resized_15_16.jpg"
},
{
  "_id": {
    "$oid": "682682b970486a0ce1ef1c3f"
  },
  "filename": "15_17.jpg",
  "text": "CcOURTYARD Mntttoll",
  "translated": "CcOURTYARD Mntttoll",
  "image_path": "resized_15_17.jpg"
},
{
  "_id": {
    "$oid": "682682c070486a0ce1ef1c40"
  },
  "filename": "15_18.jpg",
  "text": "COPLEY SYMPHONY HALL 75 0",
  "translated": "COPLEY SYMPHONY HALL 75 0",
  "image_path": "resized_15_18.jpg"
},
{
  "_id": {
    "$oid": "682682c870486a0ce1ef1c41"
  },
  "filename": "15_19.jpg",
  "text": "tehday] noutloue DESOC DEQ ] WoLidat VOLDSU 4 . JEiznou: Goddle LEFT TURN GodIA YIELI Krant",
  "translated": "tehday] new DESOC DEQ ] WoLidat VOLDSU 4 .JEiznou: GIELILITILITILITITION CentILITITION",
  "image_path": "resized_15_19.jpg"
},
{
  "_id": {
    "$oid": "682682d070486a0ce1ef1c42"
  },
  "filename": "16_00.jpg",
  "text": "HiAtI",
  "translated": "Haiti",
  "image_path": "resized_16_00.jpg"
},
{
  "_id": {
    "$oid": "682682d670486a0ce1ef1c43"
  },
  "filename": "16_01.jpg",
  "text": "WHITCOMB a HOTEL",
  "translated": "WHITCOMB a HOTEL",
  "image_path": "resized_16_01.jpg"
},
{
  "_id": {
    "$oid": "682682de70486a0ce1ef1c44"
  },
  "filename": "16_02.jpg",
  "text": "1 PARIING The MOSSER 54",
  "translated": "1 Parking the Mosser 54",
  "image_path": "resized_16_02.jpg"
},
{
  "_id": {
    "$oid": "682682e570486a0ce1ef1c45"
  },
  "filename": "16_03.jpg",
  "text": "~FOXS ~FOX WARFIELD WARFIELD WankeiSt EmtaancE HarkeiSt 26",
  "translated": "~FOXS ~FOX WARFIELD WARFIELD WankeiSt EmtaancE HarkeiSt 26",
  "image_path": "resized_16_03.jpg"
},
{
  "_id": {
    "$oid": "682682eb70486a0ce1ef1c46"
  },
  "filename": "16_04.jpg",
  "text": "HOTEL CARLTON",
  "translated": "HOTEL CARLTON",
  "image_path": "resized_16_04.jpg"
},
{
  "_id": {
    "$oid": "682682f270486a0ce1ef1c47"
  },
  "filename": "16_05.jpg",
  "text": "AMERICANIA Best Hestern HOTEL",
  "translated": "AMERICANIA Best Hestern HOTEL",
  "image_path": "resized_16_05.jpg"
},
{
  "_id": {
    "$oid": "682682f870486a0ce1ef1c48"
  },
  "filename": "16_06.jpg",
  "text": "0 C [ T Y LIG H T $ B 0 0 K $ @2009 Google 92009 G RookSTORE  LGHTS",
  "translated": "0 C [ T Y LIG H T $ B 0 0 K $ @2009 Google 92009 G RookSTORE  LGHTS",
  "image_path": "resized_16_06.jpg"
},
{
  "_id": {
    "$oid": "682682ff70486a0ce1ef1c49"
  },
  "filename": "16_07.jpg",
  "text": "BURMAASUPERSTAR Sa @Huarebi 309",
  "translated": "Burmaasuperstar in @Huarebi 309",
  "image_path": "resized_16_07.jpg"
},
{
  "_id": {
    "$oid": "6826830770486a0ce1ef1c4a"
  },
  "filename": "16_08.jpg",
  "text": "LXanda",
  "translated": "Lxanda",
  "image_path": "resized_16_08.jpg"
},
{
  "_id": {
    "$oid": "6826830e70486a0ce1ef1c4b"
  },
  "filename": "16_09.jpg",
  "text": "YANK SING",
  "translated": "YANK SING",
  "image_path": "resized_16_09.jpg"
},
{
  "_id": {
    "$oid": "6826831470486a0ce1ef1c4c"
  },
  "filename": "16_10.jpg",
  "text": "Gordon  Biersch @REWERY RESTAURANT",
  "translated": "Gordon  Biersch @REWERY RESTAURANT",
  "image_path": "resized_16_10.jpg"
},
{
  "_id": {
    "$oid": "6826831b70486a0ce1ef1c4d"
  },
  "filename": "16_12.jpg",
  "text": "brtn FRST CRUSH",
  "translated": "brtn FRST CRUSH",
  "image_path": "resized_16_12.jpg"
},
{
  "_id": {
    "$oid": "6826832170486a0ce1ef1c4e"
  },
  "filename": "16_13.jpg",
  "text": "TARA Restauramt",
  "translated": "TARA Restauramt",
  "image_path": "resized_16_13.jpg"
},
{
  "_id": {
    "$oid": "6826832770486a0ce1ef1c4f"
  },
  "filename": "16_14.jpg",
  "text": "1660 WASHINGTON SQUARE INN",
  "translated": "1660 WASHINGTON SQUARE INN",
  "image_path": "resized_16_14.jpg"
},
{
  "_id": {
    "$oid": "6826832e70486a0ce1ef1c50"
  },
  "filename": "16_15.jpg",
  "text": "Canto Do Brasil RE S TAU RA N T 41 Frankn 626-8727",
  "translated": "Canto do Brasil Restaurant 41 Frank 626-8727",
  "image_path": "resized_16_15.jpg"
},
{
  "_id": {
    "$oid": "6826833570486a0ce1ef1c51"
  },
  "filename": "16_16.jpg",
  "text": "WiCKED ORPHEUM WehiT THEATRE",
  "translated": "WiCKED ORPHEUM WehiT THEATRE",
  "image_path": "resized_16_16.jpg"
},
{
  "_id": {
    "$oid": "6826833b70486a0ce1ef1c52"
  },
  "filename": "16_17.jpg",
  "text": "PINECREST CThe Fod Mker To ZIRS SSincr 1040 RESTAURANT - Opn Z4hn Ily ARY Atm",
  "translated": "PINECREST CThe Fod Mker To ZIRS SSincr 1040 RESTAURANT - Opn Z4hn Ily ARY Atm",
  "image_path": "resized_16_17.jpg"
},
{
  "_id": {
    "$oid": "6826834370486a0ce1ef1c53"
  },
  "filename": "16_18.jpg",
  "text": "SAINT FRANCIS MEMORIAL HOSPTAL CHW 900",
  "translated": "Saint Francis Memorial Hosptal CHW 900",
  "image_path": "resized_16_18.jpg"
},
{
  "_id": {
    "$oid": "6826834970486a0ce1ef1c54"
  },
  "filename": "16_19.jpg",
  "text": "do Aneebe Mwsic FREE PARKING M IM ATe(ix #oont BUr heRED Epicori ppOle Videg",
  "translated": "do Aneebe Mwsic FREE PARKING M IM ATe(ix #oont BUr heRED Epicori ppOle Videg",
  "image_path": "resized_16_19.jpg"
},
{
  "_id": {
    "$oid": "6826834e70486a0ce1ef1c55"
  },
  "filename": "17_00.jpg",
  "text": "SAN JOSE MUSE UM 0 F A R T",
  "translated": "SAN JOSE MUSE UM 0 F A R T",
  "image_path": "resized_17_00.jpg"
},
{
  "_id": {
    "$oid": "6826835470486a0ce1ef1c56"
  },
  "filename": "17_01.jpg",
  "text": "VETNAVES Qese  Oi DAKAO RESTAURANT",
  "translated": "BETNAVES",
  "image_path": "resized_17_01.jpg"
},
{
  "_id": {
    "$oid": "6826835b70486a0ce1ef1c57"
  },
  "filename": "17_02.jpg",
  "text": "MOTIF RESTAURANT AND CLUB Suuh 7i Iel. 4uS-621-8884 M m m,Iotii Hounge €o",
  "translated": "Motif Ranger and Club Suuh 7i Iel.4US-621-8884 m m m, Iotii Hunge € O",
  "image_path": "resized_17_02.jpg"
},
{
  "_id": {
    "$oid": "6826836170486a0ce1ef1c58"
  },
  "filename": "17_03.jpg",
  "text": "131 BICYCLE EXPRESS OPEN",
  "translated": "131 BICYCLE EXPRESS OPEN",
  "image_path": "resized_17_03.jpg"
},
{
  "_id": {
    "$oid": "6826836970486a0ce1ef1c59"
  },
  "filename": "17_04.jpg",
  "text": "Gombei",
  "translated": "Gonbay",
  "image_path": "resized_17_04.jpg"
},
{
  "_id": {
    "$oid": "6826836f70486a0ce1ef1c5a"
  },
  "filename": "17_05.jpg",
  "text": "McDonaldS",
  "translated": "McDonaldS",
  "image_path": "resized_17_05.jpg"
},
{
  "_id": {
    "$oid": "6826837670486a0ce1ef1c5b"
  },
  "filename": "17_06.jpg",
  "text": "BLine ge88 408-270*4500",
  "translated": "Bline Ge88 408-270 * 4500",
  "image_path": "resized_17_06.jpg"
},
{
  "_id": {
    "$oid": "6826837c70486a0ce1ef1c5c"
  },
  "filename": "17_07.jpg",
  "text": "ERNST & YOUNG",
  "translated": "ERNST & YOUNG",
  "image_path": "resized_17_07.jpg"
},
{
  "_id": {
    "$oid": "6826838270486a0ce1ef1c5d"
  },
  "filename": "17_08.jpg",
  "text": "& # CHINESE BO TOWN VIEHNAHESE",
  "translated": "& # CHINESE BO TOWN VIEHNAHESE",
  "image_path": "resized_17_08.jpg"
},
{
  "_id": {
    "$oid": "6826838770486a0ce1ef1c5e"
  },
  "filename": "17_09.jpg",
  "text": "THE SAINTE CLAIRE",
  "translated": "THE SAINTE CLAIRE",
  "image_path": "resized_17_09.jpg"
},
{
  "_id": {
    "$oid": "6826838d70486a0ce1ef1c5f"
  },
  "filename": "17_10.jpg",
  "text": "LiqUid liqud AGENCY",
  "translated": "LiqUid liqud AGENCY",
  "image_path": "resized_17_10.jpg"
},
{
  "_id": {
    "$oid": "6826839470486a0ce1ef1c60"
  },
  "filename": "17_11.jpg",
  "text": "MIRAIDQ MILLAGE LEASING   OFFICE",
  "translated": "MIRAIDQ MILLAGE LEASING   OFFICE",
  "image_path": "resized_17_11.jpg"
},
{
  "_id": {
    "$oid": "6826839b70486a0ce1ef1c61"
  },
  "filename": "17_12.jpg",
  "text": "SushI MARU 262",
  "translated": "Sushi Maru 262",
  "image_path": "resized_17_12.jpg"
},
{
  "_id": {
    "$oid": "682683a270486a0ce1ef1c62"
  },
  "filename": "17_13.jpg",
  "text": "HIG H 5 € + 0 0 [ 4 B A ^ H ^ M LTNc 0L N",
  "translated": "HIG H 5 € + 0 0 [ 4 B A ^ H ^ M LTNc 0L N",
  "image_path": "resized_17_13.jpg"
},
{
  "_id": {
    "$oid": "682683a770486a0ce1ef1c63"
  },
  "filename": "17_14.jpg",
  "text": "E San Jose Museum o Quilts & Textiles I",
  "translated": "E San Jose Museum o Quilts & Textiles I",
  "image_path": "resized_17_14.jpg"
},
{
  "_id": {
    "$oid": "682683ae70486a0ce1ef1c64"
  },
  "filename": "17_15.jpg",
  "text": "GOODWILL",
  "translated": "GOODWILL",
  "image_path": "resized_17_15.jpg"
},
{
  "_id": {
    "$oid": "682683b370486a0ce1ef1c65"
  },
  "filename": "17_16.jpg",
  "text": "RAMADA at",
  "translated": "RAMADA at",
  "image_path": "resized_17_16.jpg"
},
{
  "_id": {
    "$oid": "682683b970486a0ce1ef1c66"
  },
  "filename": "17_17.jpg",
  "text": "FAHRENHEIT",
  "translated": "FAHRENHEIT",
  "image_path": "resized_17_17.jpg"
},
{
  "_id": {
    "$oid": "682683bf70486a0ce1ef1c67"
  },
  "filename": "17_18.jpg",
  "text": "E South FIRST BILLIARDS",
  "translated": "E South FIRST BILLIARDS",
  "image_path": "resized_17_18.jpg"
},
{
  "_id": {
    "$oid": "682683c470486a0ce1ef1c68"
  },
  "filename": "17_19.jpg",
  "text": "ANNO domini SANER MaR6 THRU Aprib",
  "translated": "ANNO domini SANER MaR6 THRU Aprib",
  "image_path": "resized_17_19.jpg"
},
{
  "_id": {
    "$oid": "682683cb70486a0ce1ef1c69"
  },
  "filename": "18_00.jpg",
  "text": "ANTICA VIA TRIBUNALL PIZZERIA",
  "translated": "Antica Via Tribunali Pizzeria",
  "image_path": "resized_18_00.jpg"
},
{
  "_id": {
    "$oid": "682683d470486a0ce1ef1c6a"
  },
  "filename": "18_01.jpg",
  "text": "Thei 'triple) k door ONLV IpakardeR_FRIn3 THE ALDUM LEAF musicquariun Mth TOOSLIMLI Tht IAILDRAGGER $ lounse",
  "translated": "Thei 'Triple) K Door Onlv iPakarder_Frin3 The Aldum Leaf Musicquriun MH toslimli Tht Iaildragger $ Lounse",
  "image_path": "resized_18_01.jpg"
},
{
  "_id": {
    "$oid": "682683da70486a0ce1ef1c6b"
  },
  "filename": "18_02.jpg",
  "text": "BLACK BOTTLE 2600 Vine ONE WAY",
  "translated": "BLACK BOTTLE 2600 Vine ONE WAY",
  "image_path": "resized_18_02.jpg"
},
{
  "_id": {
    "$oid": "682683e170486a0ce1ef1c6c"
  },
  "filename": "18_03.jpg",
  "text": "HOTECMAX",
  "translated": "HOTECMAX",
  "image_path": "resized_18_03.jpg"
},
{
  "_id": {
    "$oid": "682683e870486a0ce1ef1c6d"
  },
  "filename": "18_04.jpg",
  "text": "RDIOMIOTEL;",
  "translated": "RDIOMIOTEL;",
  "image_path": "resized_18_04.jpg"
},
{
  "_id": {
    "$oid": "682683f070486a0ce1ef1c6e"
  },
  "filename": "18_05.jpg",
  "text": "QUINNS Lunch & Dinncr h",
  "translated": "Quinns Lunch & Dinncr H",
  "image_path": "resized_18_05.jpg"
},
{
  "_id": {
    "$oid": "682683f670486a0ce1ef1c6f"
  },
  "filename": "18_06.jpg",
  "text": "T PARAMOUNT Avenuo PAREMTAL Advisorv: coradulT SituatioNS 46k FOM RuBoe JUNE 10-22 avenueq com",
  "translated": "T PARAMOUNT Avenuo PAREMTAL Advisorv: coradulT SituatioNS 46k FOM RuBoe JUNE 10-22 avenueq com",
  "image_path": "resized_18_06.jpg"
},
{
  "_id": {
    "$oid": "682683fd70486a0ce1ef1c70"
  },
  "filename": "18_07.jpg",
  "text": "THE MOORE HOTEL THEMOORE HOTEL ALTERATIONS CiTy CuSto TAILORS",
  "translated": "THE MOORE HOTEL THEMOORE HOTEL ALTERATIONS CiTy CuSto TAILORS",
  "image_path": "resized_18_07.jpg"
},
{
  "_id": {
    "$oid": "6826840470486a0ce1ef1c71"
  },
  "filename": "18_08.jpg",
  "text": "CADACE m30",
  "translated": "CADACE m30",
  "image_path": "resized_18_08.jpg"
},
{
  "_id": {
    "$oid": "6826840a70486a0ce1ef1c72"
  },
  "filename": "18_09.jpg",
  "text": "PIE AND WESTERN WINE SHOP",
  "translated": "PIE AND WESTERN WINE SHOP",
  "image_path": "resized_18_09.jpg"
},
{
  "_id": {
    "$oid": "6826841070486a0ce1ef1c73"
  },
  "filename": "18_10.jpg",
  "text": "Oo7n Western ExECUTIVE INN Best",
  "translated": "Oo7n Western ExECUTIVE INN Best",
  "image_path": "resized_18_10.jpg"
},
{
  "_id": {
    "$oid": "6826841670486a0ce1ef1c74"
  },
  "filename": "18_11.jpg",
  "text": "#ntnntnnttt 13 The EXECUTIVE HOTEL PACIFIC",
  "translated": "#ntnntnnttt 13 The EXECUTIVE HOTEL PACIFIC",
  "image_path": "resized_18_11.jpg"
},
{
  "_id": {
    "$oid": "6826841e70486a0ce1ef1c75"
  },
  "filename": "18_12.jpg",
  "text": "Rrei",
  "translated": "Rrei",
  "image_path": "resized_18_12.jpg"
},
{
  "_id": {
    "$oid": "6826842570486a0ce1ef1c76"
  },
  "filename": "18_13.jpg",
  "text": "E Best LOYAL Western  INN",
  "translated": "E Best LOYAL Western  INN",
  "image_path": "resized_18_13.jpg"
},
{
  "_id": {
    "$oid": "6826842d70486a0ce1ef1c77"
  },
  "filename": "18_14.jpg",
  "text": "Ea Iroinia m Lola ONE WAY",
  "translated": "Joiini M Lola One Way",
  "image_path": "resized_18_14.jpg"
},
{
  "_id": {
    "$oid": "6826843370486a0ce1ef1c78"
  },
  "filename": "18_15.jpg",
  "text": "RIXTHAVENUE BAR & GRILL {h Rragw LHELEE",
  "translated": "RIXTHAVENUE BAR & GRILL {h Rragw LHELEE",
  "image_path": "resized_18_15.jpg"
},
{
  "_id": {
    "$oid": "6826843a70486a0ce1ef1c79"
  },
  "filename": "18_16.jpg",
  "text": "94 Stewart RESTAURANT",
  "translated": "94 Stewart RESTAURANT",
  "image_path": "resized_18_16.jpg"
},
{
  "_id": {
    "$oid": "6826844170486a0ce1ef1c7a"
  },
  "filename": "18_17.jpg",
  "text": "CINERAMA wwWcinerama.com",
  "translated": "CINERAMA wwWcinerama.com",
  "image_path": "resized_18_17.jpg"
},
{
  "_id": {
    "$oid": "6826844970486a0ce1ef1c7b"
  },
  "filename": "18_18.jpg",
  "text": "GARFIELD HIGH SCHOOL AT LINCOLN",
  "translated": "GARFIELD HIGH SCHOOL AT LINCOLN",
  "image_path": "resized_18_18.jpg"
},
{
  "_id": {
    "$oid": "6826845170486a0ce1ef1c7c"
  },
  "filename": "18_19.jpg",
  "text": "NEtMOS LTCONIKC #or",
  "translated": "NEtMOS LTCONIKC #or",
  "image_path": "resized_18_19.jpg"
},
{
  "_id": {
    "$oid": "6826845970486a0ce1ef1c7d"
  },
  "filename": "19_00.jpg",
  "text": "Restaurant Cafe Soleil Bar",
  "translated": "Restaurant Cafe Soleil Bar",
  "image_path": "resized_19_00.jpg"
},
{
  "_id": {
    "$oid": "6826846170486a0ce1ef1c7e"
  },
  "filename": "19_01.jpg",
  "text": "TINY JEWEL BOX",
  "translated": "TINY JEWEL BOX",
  "image_path": "resized_19_01.jpg"
},
{
  "_id": {
    "$oid": "6826846a70486a0ce1ef1c7f"
  },
  "filename": "19_03.jpg",
  "text": "24 CVSIpharmacy HOURS Cvs/pharmecy CvS/ pharmacy Gublcharmaci",
  "translated": "24 CVSIpharmacy HOURS Cvs/pharmecy CvS/ pharmacy Gublcharmaci",
  "image_path": "resized_19_03.jpg"
},
{
  "_id": {
    "$oid": "6826847470486a0ce1ef1c80"
  },
  "filename": "19_04.jpg",
  "text": "LRI same DAI fraMung kul OMA FRA Ing GROCERY-BEER & 196 DELICATESSEF SAKANA JAPANESE RESIAURANT 24",
  "translated": "LRI FRO IS ON FRA",
  "image_path": "resized_19_04.jpg"
},
{
  "_id": {
    "$oid": "6826847c70486a0ce1ef1c81"
  },
  "filename": "19_06.jpg",
  "text": "1 5 LIQUOR BE THE FREPLACE AtM SAMUL Fuuo NTS rdmnd",
  "translated": "1 5 LIQUOR BE THE FREPLACE AtM SAMUL Fuuo NTS rdmnd",
  "image_path": "resized_19_06.jpg"
},
{
  "_id": {
    "$oid": "6826848470486a0ce1ef1c82"
  },
  "filename": "19_07.jpg",
  "text": "ERS AND CLEANERS WM FOX & CO: 1425 1427 SHOE DRT REPAIR & CLEANINC TAlloRIG CPEN GAN JuMMO Ya EAPERT",
  "translated": "ERS AND CLEANERS WM FOX & CO: 1425 1427 SHOE DRT REPAIR & CLEANINC TAlloRIG CPEN GAN JuMMO Ya EAPERT",
  "image_path": "resized_19_07.jpg"
},
{
  "_id": {
    "$oid": "6826848d70486a0ce1ef1c83"
  },
  "filename": "19_09.jpg",
  "text": "utique Books  for  America dooneT00 Fico bookslorumerica orp OPEN",
  "translated": "Of course books for America Doonet00 Fig Booklorumerica Orp open",
  "image_path": "resized_19_09.jpg"
},
{
  "_id": {
    "$oid": "6826849670486a0ce1ef1c84"
  },
  "filename": "19_11.jpg",
  "text": "BUITAR Sthe GUTAIRC SHOP FUDDRUCKERS Fnesh Gnound Garden Fnesh Prduce Fneh Baked Bnead QTAR S4Op Or IFudds pRIME ONE 00% brEA MLRIcAN WAY prEMIUEA Dccr Beek",
  "translated": "Buitar Ste Gutairc Shop Fuddruers Fnesh Gnoound garden netch network neh baked bnead s4op or Ifudds Prime One 00% Brea mlrican premiueaa dcc",
  "image_path": "resized_19_11.jpg"
},
{
  "_id": {
    "$oid": "6826849e70486a0ce1ef1c85"
  },
  "filename": "19_12.jpg",
  "text": "met €afe eaablaE paeuieg Hour Imakinc ",
  "translated": "met €afe eaablaE paeuieg Hour Imakinc",
  "image_path": "resized_19_12.jpg"
},
{
  "_id": {
    "$oid": "682684a670486a0ce1ef1c86"
  },
  "filename": "19_13.jpg",
  "text": "6 PMD ING LOUNE CHOCOLATE MOOSE JapER Plastic?  agtitco",
  "translated": "6 PMD ING LOUNE CHOCOLATE MOOSE JapER Plastic?  agtitco",
  "image_path": "resized_19_13.jpg"
}]